{
"meta":{"test_sets":[],"test_metrics":[],"learn_metrics":[{"best_value":"Min","name":"Logloss"}],"launch_mode":"Train","parameters":"","iteration_count":500,"learn_sets":["learn"],"name":"experiment"},
"iterations":[
{"learn":[0.5643314229],"iteration":0,"passed_time":0.00174462186,"remaining_time":0.870566308},
{"learn":[0.4682758964],"iteration":1,"passed_time":0.003423354966,"remaining_time":0.8524153864},
{"learn":[0.4190744148],"iteration":2,"passed_time":0.004809473516,"remaining_time":0.7967694458},
{"learn":[0.3773136494],"iteration":3,"passed_time":0.006227946296,"remaining_time":0.7722653407},
{"learn":[0.3482273227],"iteration":4,"passed_time":0.007624261391,"remaining_time":0.7548018777},
{"learn":[0.3238502477],"iteration":5,"passed_time":0.009003953211,"remaining_time":0.741325481},
{"learn":[0.3137738948],"iteration":6,"passed_time":0.01040129097,"remaining_time":0.7325480639},
{"learn":[0.2949226953],"iteration":7,"passed_time":0.0119301812,"remaining_time":0.733706144},
{"learn":[0.2819349968],"iteration":8,"passed_time":0.01334153545,"remaining_time":0.7278548785},
{"learn":[0.2677664966],"iteration":9,"passed_time":0.01474892939,"remaining_time":0.7226975401},
{"learn":[0.2576860508],"iteration":10,"passed_time":0.01615297461,"remaining_time":0.718073144},
{"learn":[0.2498033565],"iteration":11,"passed_time":0.01757424467,"remaining_time":0.7146859499},
{"learn":[0.2340629905],"iteration":12,"passed_time":0.01903201977,"remaining_time":0.7129687405},
{"learn":[0.2252909267],"iteration":13,"passed_time":0.0203768007,"remaining_time":0.7073660815},
{"learn":[0.2200829683],"iteration":14,"passed_time":0.0218179425,"remaining_time":0.7054468074},
{"learn":[0.2159341693],"iteration":15,"passed_time":0.02332846491,"remaining_time":0.7056860637},
{"learn":[0.2093356694],"iteration":16,"passed_time":0.02521865574,"remaining_time":0.7165065131},
{"learn":[0.2054261242],"iteration":17,"passed_time":0.02677304736,"remaining_time":0.7169227128},
{"learn":[0.1966077917],"iteration":18,"passed_time":0.02832172912,"remaining_time":0.716986932},
{"learn":[0.1940753227],"iteration":19,"passed_time":0.02983399553,"remaining_time":0.7160158926},
{"learn":[0.1885342563],"iteration":20,"passed_time":0.03133639736,"remaining_time":0.7147683016},
{"learn":[0.1884213018],"iteration":21,"passed_time":0.03222212321,"remaining_time":0.7000988589},
{"learn":[0.1841035629],"iteration":22,"passed_time":0.0337255867,"remaining_time":0.6994393415},
{"learn":[0.182144395],"iteration":23,"passed_time":0.03500969969,"remaining_time":0.6943590439},
{"learn":[0.1775928284],"iteration":24,"passed_time":0.03638242393,"remaining_time":0.6912660546},
{"learn":[0.1688978522],"iteration":25,"passed_time":0.03779162256,"remaining_time":0.6889703498},
{"learn":[0.1628770044],"iteration":26,"passed_time":0.03917343991,"remaining_time":0.6862606326},
{"learn":[0.1592392095],"iteration":27,"passed_time":0.04052443703,"remaining_time":0.6831262242},
{"learn":[0.1544201271],"iteration":28,"passed_time":0.04191554858,"remaining_time":0.6807663235},
{"learn":[0.150180827],"iteration":29,"passed_time":0.04326013902,"remaining_time":0.677742178},
{"learn":[0.1469309532],"iteration":30,"passed_time":0.04462678688,"remaining_time":0.6751600983},
{"learn":[0.1444264484],"iteration":31,"passed_time":0.04594417651,"remaining_time":0.6719335814},
{"learn":[0.1394238712],"iteration":32,"passed_time":0.04739428163,"remaining_time":0.6707008947},
{"learn":[0.1347693541],"iteration":33,"passed_time":0.04879903871,"remaining_time":0.6688338835},
{"learn":[0.1312992162],"iteration":34,"passed_time":0.05015620188,"remaining_time":0.6663609678},
{"learn":[0.1293604545],"iteration":35,"passed_time":0.05150689821,"remaining_time":0.6638666881},
{"learn":[0.1255789073],"iteration":36,"passed_time":0.05287954168,"remaining_time":0.6617088594},
{"learn":[0.1212414081],"iteration":37,"passed_time":0.05426137909,"remaining_time":0.6597041352},
{"learn":[0.1176887255],"iteration":38,"passed_time":0.05563886516,"remaining_time":0.657679919},
{"learn":[0.1148319716],"iteration":39,"passed_time":0.05699669006,"remaining_time":0.6554619356},
{"learn":[0.1120082579],"iteration":40,"passed_time":0.05836337746,"remaining_time":0.6533851282},
{"learn":[0.1092936926],"iteration":41,"passed_time":0.05973035619,"remaining_time":0.6513453127},
{"learn":[0.1072463038],"iteration":42,"passed_time":0.06106562235,"remaining_time":0.6489997538},
{"learn":[0.1044766711],"iteration":43,"passed_time":0.06247631543,"remaining_time":0.6474818145},
{"learn":[0.1012137619],"iteration":44,"passed_time":0.06405684009,"remaining_time":0.6476858276},
{"learn":[0.09974208671],"iteration":45,"passed_time":0.06554768127,"remaining_time":0.6469271151},
{"learn":[0.09854572882],"iteration":46,"passed_time":0.0670852853,"remaining_time":0.6465879626},
{"learn":[0.09745903142],"iteration":47,"passed_time":0.06872655699,"remaining_time":0.6471750784},
{"learn":[0.09611960182],"iteration":48,"passed_time":0.07041253563,"remaining_time":0.6480827259},
{"learn":[0.09457879766],"iteration":49,"passed_time":0.07184745177,"remaining_time":0.6466270659},
{"learn":[0.09363229663],"iteration":50,"passed_time":0.07319091929,"remaining_time":0.6443671129},
{"learn":[0.09301413014],"iteration":51,"passed_time":0.07457007972,"remaining_time":0.6424499176},
{"learn":[0.09041097025],"iteration":52,"passed_time":0.07596331681,"remaining_time":0.6406717474},
{"learn":[0.08863943931],"iteration":53,"passed_time":0.07748390543,"remaining_time":0.6399596633},
{"learn":[0.08838000873],"iteration":54,"passed_time":0.07879468785,"remaining_time":0.6375206563},
{"learn":[0.08635423638],"iteration":55,"passed_time":0.08015242251,"remaining_time":0.635494207},
{"learn":[0.08502328829],"iteration":56,"passed_time":0.08148321703,"remaining_time":0.6332818447},
{"learn":[0.08443085218],"iteration":57,"passed_time":0.08280517856,"remaining_time":0.6310325676},
{"learn":[0.08287068754],"iteration":58,"passed_time":0.08416926976,"remaining_time":0.6291296265},
{"learn":[0.08237280357],"iteration":59,"passed_time":0.08546517345,"remaining_time":0.6267446053},
{"learn":[0.08203991892],"iteration":60,"passed_time":0.08682129391,"remaining_time":0.6248286562},
{"learn":[0.08095818289],"iteration":61,"passed_time":0.08816138263,"remaining_time":0.6228175095},
{"learn":[0.07998454383],"iteration":62,"passed_time":0.08949495438,"remaining_time":0.6207824613},
{"learn":[0.07835872932],"iteration":63,"passed_time":0.09086224391,"remaining_time":0.6189990367},
{"learn":[0.07604082306],"iteration":64,"passed_time":0.09232918287,"remaining_time":0.6178953007},
{"learn":[0.07503116052],"iteration":65,"passed_time":0.0937454098,"remaining_time":0.6164470887},
{"learn":[0.07313755329],"iteration":66,"passed_time":0.09510979176,"remaining_time":0.6146647736},
{"learn":[0.07290051237],"iteration":67,"passed_time":0.09636758624,"remaining_time":0.6122176067},
{"learn":[0.07083403791],"iteration":68,"passed_time":0.09776065288,"remaining_time":0.6106498752},
{"learn":[0.0688437419],"iteration":69,"passed_time":0.09911776592,"remaining_time":0.6088662764},
{"learn":[0.06843565341],"iteration":70,"passed_time":0.1004622661,"remaining_time":0.6070184812},
{"learn":[0.06690524339],"iteration":71,"passed_time":0.1017880576,"remaining_time":0.6050734536},
{"learn":[0.064820832],"iteration":72,"passed_time":0.1031935065,"remaining_time":0.6036113325},
{"learn":[0.06413685002],"iteration":73,"passed_time":0.1045774694,"remaining_time":0.6020270538},
{"learn":[0.06330700133],"iteration":74,"passed_time":0.1059316448,"remaining_time":0.6002793207},
{"learn":[0.06267853393],"iteration":75,"passed_time":0.1075070272,"remaining_time":0.5997760465},
{"learn":[0.06064534732],"iteration":76,"passed_time":0.1090087957,"remaining_time":0.5988405271},
{"learn":[0.06027685876],"iteration":77,"passed_time":0.1103515815,"remaining_time":0.597030351},
{"learn":[0.05908464117],"iteration":78,"passed_time":0.1117331181,"remaining_time":0.5954385154},
{"learn":[0.05794978932],"iteration":79,"passed_time":0.1131305862,"remaining_time":0.5939355774},
{"learn":[0.05718567337],"iteration":80,"passed_time":0.1145239636,"remaining_time":0.5924140835},
{"learn":[0.05560942916],"iteration":81,"passed_time":0.1158848866,"remaining_time":0.5907302755},
{"learn":[0.05425938927],"iteration":82,"passed_time":0.117200271,"remaining_time":0.5888254579},
{"learn":[0.05376729901],"iteration":83,"passed_time":0.1185007566,"remaining_time":0.5868608899},
{"learn":[0.05272913766],"iteration":84,"passed_time":0.1198906851,"remaining_time":0.5853486389},
{"learn":[0.05254793722],"iteration":85,"passed_time":0.1211447498,"remaining_time":0.5831851911},
{"learn":[0.05229408607],"iteration":86,"passed_time":0.1225954365,"remaining_time":0.5819760376},
{"learn":[0.05199379455],"iteration":87,"passed_time":0.1239760106,"remaining_time":0.5804331406},
{"learn":[0.05103096179],"iteration":88,"passed_time":0.1254390193,"remaining_time":0.5792745724},
{"learn":[0.05044962723],"iteration":89,"passed_time":0.1268647109,"remaining_time":0.5779392385},
{"learn":[0.04963959081],"iteration":90,"passed_time":0.128306735,"remaining_time":0.5766753254},
{"learn":[0.04913817197],"iteration":91,"passed_time":0.1296387828,"remaining_time":0.5749198193},
{"learn":[0.04785051756],"iteration":92,"passed_time":0.1310738688,"remaining_time":0.5736243506},
{"learn":[0.04748820605],"iteration":93,"passed_time":0.1324057662,"remaining_time":0.5718802242},
{"learn":[0.04668030683],"iteration":94,"passed_time":0.1338008381,"remaining_time":0.5704140991},
{"learn":[0.04555729195],"iteration":95,"passed_time":0.1352056152,"remaining_time":0.5689902972},
{"learn":[0.04457049255],"iteration":96,"passed_time":0.1365464057,"remaining_time":0.5673010465},
{"learn":[0.04358761662],"iteration":97,"passed_time":0.1381266898,"remaining_time":0.5666013192},
{"learn":[0.0432020142],"iteration":98,"passed_time":0.1394858882,"remaining_time":0.5649882947},
{"learn":[0.04257367331],"iteration":99,"passed_time":0.1408777016,"remaining_time":0.5635108064},
{"learn":[0.04166066473],"iteration":100,"passed_time":0.1422948409,"remaining_time":0.5621350646},
{"learn":[0.04118270004],"iteration":101,"passed_time":0.1436414265,"remaining_time":0.5604832134},
{"learn":[0.04084589384],"iteration":102,"passed_time":0.1449796304,"remaining_time":0.558804983},
{"learn":[0.04039717059],"iteration":103,"passed_time":0.1463653378,"remaining_time":0.557314171},
{"learn":[0.03939801111],"iteration":104,"passed_time":0.1477965738,"remaining_time":0.5559966349},
{"learn":[0.03870768141],"iteration":105,"passed_time":0.1491655578,"remaining_time":0.5544455639},
{"learn":[0.03820502114],"iteration":106,"passed_time":0.1505382113,"remaining_time":0.5529113742},
{"learn":[0.03790565555],"iteration":107,"passed_time":0.1520657179,"remaining_time":0.5519422354},
{"learn":[0.03766275384],"iteration":108,"passed_time":0.1537141293,"remaining_time":0.5513965556},
{"learn":[0.03747015998],"iteration":109,"passed_time":0.1551423374,"remaining_time":0.5500501054},
{"learn":[0.03716664859],"iteration":110,"passed_time":0.156477002,"remaining_time":0.5483743585},
{"learn":[0.03671413158],"iteration":111,"passed_time":0.1578989438,"remaining_time":0.5470070554},
{"learn":[0.03632345124],"iteration":112,"passed_time":0.159263777,"remaining_time":0.5454432008},
{"learn":[0.03584049654],"iteration":113,"passed_time":0.1606545527,"remaining_time":0.5439706783},
{"learn":[0.03552920162],"iteration":114,"passed_time":0.1619955036,"remaining_time":0.542332773},
{"learn":[0.03496768614],"iteration":115,"passed_time":0.1633703127,"remaining_time":0.5408120697},
{"learn":[0.03441939311],"iteration":116,"passed_time":0.1648269248,"remaining_time":0.5395616427},
{"learn":[0.03406373714],"iteration":117,"passed_time":0.166412658,"remaining_time":0.5387257234},
{"learn":[0.03351064665],"iteration":118,"passed_time":0.1681443713,"remaining_time":0.5383445836},
{"learn":[0.03304443946],"iteration":119,"passed_time":0.169873949,"remaining_time":0.5379341717},
{"learn":[0.03297061465],"iteration":120,"passed_time":0.1715311583,"remaining_time":0.5372752808},
{"learn":[0.03262849869],"iteration":121,"passed_time":0.1732195237,"remaining_time":0.5366965569},
{"learn":[0.03223330948],"iteration":122,"passed_time":0.1747913156,"remaining_time":0.5357424876},
{"learn":[0.03161664488],"iteration":123,"passed_time":0.1764942138,"remaining_time":0.5351760032},
{"learn":[0.03133317863],"iteration":124,"passed_time":0.1780588571,"remaining_time":0.5341765714},
{"learn":[0.03087869106],"iteration":125,"passed_time":0.179616432,"remaining_time":0.5331471872},
{"learn":[0.03034241639],"iteration":126,"passed_time":0.1812277719,"remaining_time":0.5322673931},
{"learn":[0.02982213376],"iteration":127,"passed_time":0.1827567173,"remaining_time":0.5311367097},
{"learn":[0.02946210312],"iteration":128,"passed_time":0.1843272058,"remaining_time":0.5301193284},
{"learn":[0.02888548663],"iteration":129,"passed_time":0.1858918993,"remaining_time":0.5290769441},
{"learn":[0.02859051584],"iteration":130,"passed_time":0.1875581972,"remaining_time":0.5283127846},
{"learn":[0.02813655305],"iteration":131,"passed_time":0.1892017861,"remaining_time":0.527471646},
{"learn":[0.02789655811],"iteration":132,"passed_time":0.1906504926,"remaining_time":0.5260806825},
{"learn":[0.0274500774],"iteration":133,"passed_time":0.1920648647,"remaining_time":0.5245950781},
{"learn":[0.0271971119],"iteration":134,"passed_time":0.1933854025,"remaining_time":0.5228568289},
{"learn":[0.02692348977],"iteration":135,"passed_time":0.1947498446,"remaining_time":0.5212422311},
{"learn":[0.02657676244],"iteration":136,"passed_time":0.1961295164,"remaining_time":0.5196716383},
{"learn":[0.02636947684],"iteration":137,"passed_time":0.1975411714,"remaining_time":0.5181877105},
{"learn":[0.02612230449],"iteration":138,"passed_time":0.1989937324,"remaining_time":0.5168110603},
{"learn":[0.02589141414],"iteration":139,"passed_time":0.2003472059,"remaining_time":0.5151785295},
{"learn":[0.02578776895],"iteration":140,"passed_time":0.2016942528,"remaining_time":0.5135335939},
{"learn":[0.02560593138],"iteration":141,"passed_time":0.2030881922,"remaining_time":0.5120110762},
{"learn":[0.02535456815],"iteration":142,"passed_time":0.2044221149,"remaining_time":0.5103405246},
{"learn":[0.02500262887],"iteration":143,"passed_time":0.2057684599,"remaining_time":0.5087053592},
{"learn":[0.02476764827],"iteration":144,"passed_time":0.2070993046,"remaining_time":0.5070362284},
{"learn":[0.02447638417],"iteration":145,"passed_time":0.2084726298,"remaining_time":0.5054747325},
{"learn":[0.02435810505],"iteration":146,"passed_time":0.2097648138,"remaining_time":0.5037209474},
{"learn":[0.02422159814],"iteration":147,"passed_time":0.2110899737,"remaining_time":0.5020518292},
{"learn":[0.02410903445],"iteration":148,"passed_time":0.212479862,"remaining_time":0.5005398092},
{"learn":[0.02402410413],"iteration":149,"passed_time":0.2138675547,"remaining_time":0.4990242942},
{"learn":[0.02376616215],"iteration":150,"passed_time":0.2152600398,"remaining_time":0.4975215489},
{"learn":[0.02334204812],"iteration":151,"passed_time":0.2166449853,"remaining_time":0.4960029926},
{"learn":[0.02311625539],"iteration":152,"passed_time":0.2180154832,"remaining_time":0.4944534161},
{"learn":[0.02291263147],"iteration":153,"passed_time":0.2193709018,"remaining_time":0.4928722859},
{"learn":[0.02266976828],"iteration":154,"passed_time":0.2207920114,"remaining_time":0.4914402835},
{"learn":[0.0225754249],"iteration":155,"passed_time":0.2221518416,"remaining_time":0.4898732916},
{"learn":[0.02243737564],"iteration":156,"passed_time":0.2234690006,"remaining_time":0.4882157147},
{"learn":[0.02225134083],"iteration":157,"passed_time":0.2248007376,"remaining_time":0.4865940016},
{"learn":[0.0219445893],"iteration":158,"passed_time":0.2261878487,"remaining_time":0.4850946944},
{"learn":[0.02178075188],"iteration":159,"passed_time":0.2275703779,"remaining_time":0.483587053},
{"learn":[0.02162248129],"iteration":160,"passed_time":0.2289518042,"remaining_time":0.4820786437},
{"learn":[0.02144859424],"iteration":161,"passed_time":0.2302629977,"remaining_time":0.4804252669},
{"learn":[0.02140257755],"iteration":162,"passed_time":0.2315870046,"remaining_time":0.47880258},
{"learn":[0.02119209913],"iteration":163,"passed_time":0.2329476969,"remaining_time":0.4772586962},
{"learn":[0.02109982597],"iteration":164,"passed_time":0.2342999674,"remaining_time":0.4756999338},
{"learn":[0.02090033074],"iteration":165,"passed_time":0.2356640686,"remaining_time":0.4741674633},
{"learn":[0.02083839697],"iteration":166,"passed_time":0.2369726152,"remaining_time":0.4725262327},
{"learn":[0.02057388741],"iteration":167,"passed_time":0.2383397343,"remaining_time":0.471004713},
{"learn":[0.02038270989],"iteration":168,"passed_time":0.2396852471,"remaining_time":0.469442703},
{"learn":[0.02014347971],"iteration":169,"passed_time":0.2410380991,"remaining_time":0.4678974864},
{"learn":[0.01996446151],"iteration":170,"passed_time":0.2424349155,"remaining_time":0.4664391064},
{"learn":[0.01973209158],"iteration":171,"passed_time":0.2438702923,"remaining_time":0.465054976},
{"learn":[0.01956150478],"iteration":172,"passed_time":0.2453206781,"remaining_time":0.4636986228},
{"learn":[0.01937668991],"iteration":173,"passed_time":0.2467415672,"remaining_time":0.4622859248},
{"learn":[0.01917005627],"iteration":174,"passed_time":0.2481126767,"remaining_time":0.4607806853},
{"learn":[0.01906210237],"iteration":175,"passed_time":0.249463744,"remaining_time":0.4592400741},
{"learn":[0.01887428553],"iteration":176,"passed_time":0.2508735241,"remaining_time":0.4578087474},
{"learn":[0.01868526109],"iteration":177,"passed_time":0.2522315796,"remaining_time":0.4562840935},
{"learn":[0.0185833165],"iteration":178,"passed_time":0.253545029,"remaining_time":0.454681309},
{"learn":[0.0185245274],"iteration":179,"passed_time":0.2549051799,"remaining_time":0.4531647643},
{"learn":[0.01831609216],"iteration":180,"passed_time":0.2562749259,"remaining_time":0.4516668583},
{"learn":[0.01827621243],"iteration":181,"passed_time":0.2576088385,"remaining_time":0.4501077508},
{"learn":[0.01824868499],"iteration":182,"passed_time":0.2590666838,"remaining_time":0.4487657856},
{"learn":[0.01822457386],"iteration":183,"passed_time":0.260408868,"remaining_time":0.4472239254},
{"learn":[0.01798374685],"iteration":184,"passed_time":0.2618010824,"remaining_time":0.4457694105},
{"learn":[0.01780116865],"iteration":185,"passed_time":0.2631481292,"remaining_time":0.4442393149},
{"learn":[0.01764021385],"iteration":186,"passed_time":0.2645036481,"remaining_time":0.4427253575},
{"learn":[0.01754519205],"iteration":187,"passed_time":0.26583344,"remaining_time":0.4411703898},
{"learn":[0.01738184678],"iteration":188,"passed_time":0.2671840361,"remaining_time":0.4396520382},
{"learn":[0.01723459382],"iteration":189,"passed_time":0.268577584,"remaining_time":0.4382055317},
{"learn":[0.01703554625],"iteration":190,"passed_time":0.2699416551,"remaining_time":0.4367118923},
{"learn":[0.01693032429],"iteration":191,"passed_time":0.2712982669,"remaining_time":0.4352076364},
{"learn":[0.01677833562],"iteration":192,"passed_time":0.2726397392,"remaining_time":0.4336808286},
{"learn":[0.01663395222],"iteration":193,"passed_time":0.2741053647,"remaining_time":0.4323517608},
{"learn":[0.0165593988],"iteration":194,"passed_time":0.2754425459,"remaining_time":0.4308203922},
{"learn":[0.01643469413],"iteration":195,"passed_time":0.2768022757,"remaining_time":0.4293259787},
{"learn":[0.01627614403],"iteration":196,"passed_time":0.2781546464,"remaining_time":0.4278216135},
{"learn":[0.01608934353],"iteration":197,"passed_time":0.27957727,"remaining_time":0.4264259371},
{"learn":[0.01592230354],"iteration":198,"passed_time":0.2809494322,"remaining_time":0.4249536638},
{"learn":[0.01583852883],"iteration":199,"passed_time":0.2823194488,"remaining_time":0.4234791733},
{"learn":[0.01570640994],"iteration":200,"passed_time":0.2836453707,"remaining_time":0.4219401285},
{"learn":[0.0156519833],"iteration":201,"passed_time":0.2849459064,"remaining_time":0.4203657431},
{"learn":[0.01559907781],"iteration":202,"passed_time":0.2862680484,"remaining_time":0.4188256669},
{"learn":[0.01548127742],"iteration":203,"passed_time":0.287607706,"remaining_time":0.4173131421},
{"learn":[0.01545237693],"iteration":204,"passed_time":0.2889312517,"remaining_time":0.4157791183},
{"learn":[0.01536433337],"iteration":205,"passed_time":0.2903335122,"remaining_time":0.4143594786},
{"learn":[0.01525994578],"iteration":206,"passed_time":0.2917604471,"remaining_time":0.4129749323},
{"learn":[0.01522992899],"iteration":207,"passed_time":0.2930701968,"remaining_time":0.4114254686},
{"learn":[0.01521051491],"iteration":208,"passed_time":0.2944189982,"remaining_time":0.4099326721},
{"learn":[0.01509719733],"iteration":209,"passed_time":0.2958152832,"remaining_time":0.4085068197},
{"learn":[0.01499842418],"iteration":210,"passed_time":0.297203808,"remaining_time":0.4070706186},
{"learn":[0.01495631704],"iteration":211,"passed_time":0.298567027,"remaining_time":0.4056004895},
{"learn":[0.01493921113],"iteration":212,"passed_time":0.2999160389,"remaining_time":0.4041122214},
{"learn":[0.0148862925],"iteration":213,"passed_time":0.301293926,"remaining_time":0.4026638451},
{"learn":[0.01469965265],"iteration":214,"passed_time":0.3026889778,"remaining_time":0.4012388776},
{"learn":[0.01461914393],"iteration":215,"passed_time":0.3042017361,"remaining_time":0.3999689493},
{"learn":[0.01456864471],"iteration":216,"passed_time":0.3055483518,"remaining_time":0.3984801085},
{"learn":[0.01450647986],"iteration":217,"passed_time":0.3068500506,"remaining_time":0.3969344691},
{"learn":[0.01435784126],"iteration":218,"passed_time":0.3082327302,"remaining_time":0.3954949643},
{"learn":[0.01428129836],"iteration":219,"passed_time":0.3095471521,"remaining_time":0.3939691026},
{"learn":[0.01419199506],"iteration":220,"passed_time":0.3109148426,"remaining_time":0.3925124031},
{"learn":[0.01405603587],"iteration":221,"passed_time":0.3122770088,"remaining_time":0.3910495876},
{"learn":[0.01395685931],"iteration":222,"passed_time":0.3136083147,"remaining_time":0.3895493416},
{"learn":[0.01387134515],"iteration":223,"passed_time":0.3149692276,"remaining_time":0.388087084},
{"learn":[0.0137877744],"iteration":224,"passed_time":0.3163397756,"remaining_time":0.3866375035},
{"learn":[0.01369187138],"iteration":225,"passed_time":0.3176634717,"remaining_time":0.3851318196},
{"learn":[0.01364381823],"iteration":226,"passed_time":0.3189610798,"remaining_time":0.3835963647},
{"learn":[0.0135227926],"iteration":227,"passed_time":0.3205752119,"remaining_time":0.3824406037},
{"learn":[0.01344574151],"iteration":228,"passed_time":0.3221091247,"remaining_time":0.3811859074},
{"learn":[0.01334576212],"iteration":229,"passed_time":0.3237297153,"remaining_time":0.3800305354},
{"learn":[0.01331296776],"iteration":230,"passed_time":0.3250975552,"remaining_time":0.3785768067},
{"learn":[0.01329744413],"iteration":231,"passed_time":0.3263850771,"remaining_time":0.3770310373},
{"learn":[0.01328408024],"iteration":232,"passed_time":0.3277207242,"remaining_time":0.3755426325},
{"learn":[0.01324556021],"iteration":233,"passed_time":0.3290089479,"remaining_time":0.3740016245},
{"learn":[0.013196977],"iteration":234,"passed_time":0.3303685274,"remaining_time":0.372543233},
{"learn":[0.01318528905],"iteration":235,"passed_time":0.3316680705,"remaining_time":0.3710185196},
{"learn":[0.01308279036],"iteration":236,"passed_time":0.3330170023,"remaining_time":0.3695505131},
{"learn":[0.01296164983],"iteration":237,"passed_time":0.3345615382,"remaining_time":0.3682988362},
{"learn":[0.01287960851],"iteration":238,"passed_time":0.3359190222,"remaining_time":0.3668404385},
{"learn":[0.01282252266],"iteration":239,"passed_time":0.3373063539,"remaining_time":0.3654152168},
{"learn":[0.01276500447],"iteration":240,"passed_time":0.3386783257,"remaining_time":0.3639738023},
{"learn":[0.0127510322],"iteration":241,"passed_time":0.3400143438,"remaining_time":0.362494631},
{"learn":[0.01264747962],"iteration":242,"passed_time":0.3414734273,"remaining_time":0.3611467935},
{"learn":[0.0125576626],"iteration":243,"passed_time":0.3428408672,"remaining_time":0.3597018935},
{"learn":[0.01249325723],"iteration":244,"passed_time":0.3441942305,"remaining_time":0.3582429746},
{"learn":[0.01240770216],"iteration":245,"passed_time":0.3456157512,"remaining_time":0.3568552878},
{"learn":[0.01236563008],"iteration":246,"passed_time":0.3470156155,"remaining_time":0.3554451447},
{"learn":[0.012279779],"iteration":247,"passed_time":0.3485067269,"remaining_time":0.3541278031},
{"learn":[0.01220815055],"iteration":248,"passed_time":0.3498431059,"remaining_time":0.3526530907},
{"learn":[0.01216986179],"iteration":249,"passed_time":0.3511645662,"remaining_time":0.3511645662},
{"learn":[0.01213966035],"iteration":250,"passed_time":0.3524942695,"remaining_time":0.3496855502},
{"learn":[0.01205788274],"iteration":251,"passed_time":0.3538722157,"remaining_time":0.3482551964},
{"learn":[0.01200893455],"iteration":252,"passed_time":0.3551877605,"remaining_time":0.3467643353},
{"learn":[0.01193735088],"iteration":253,"passed_time":0.3565498766,"remaining_time":0.3453199592},
{"learn":[0.01186625519],"iteration":254,"passed_time":0.3579142485,"remaining_time":0.3438783956},
{"learn":[0.0117435311],"iteration":255,"passed_time":0.3592721937,"remaining_time":0.3424313096},
{"learn":[0.01165119733],"iteration":256,"passed_time":0.3606611697,"remaining_time":0.3410142577},
{"learn":[0.01159709564],"iteration":257,"passed_time":0.3619952528,"remaining_time":0.3395459348},
{"learn":[0.01156402651],"iteration":258,"passed_time":0.3634367605,"remaining_time":0.3381786073},
{"learn":[0.01147174397],"iteration":259,"passed_time":0.3648558048,"remaining_time":0.3367899736},
{"learn":[0.01140568206],"iteration":260,"passed_time":0.3661818068,"remaining_time":0.3353159074},
{"learn":[0.01135863838],"iteration":261,"passed_time":0.3675030665,"remaining_time":0.3338386635},
{"learn":[0.01132197626],"iteration":262,"passed_time":0.3688657441,"remaining_time":0.3323999291},
{"learn":[0.01124073686],"iteration":263,"passed_time":0.3702364625,"remaining_time":0.3309689589},
{"learn":[0.01121226069],"iteration":264,"passed_time":0.3715338601,"remaining_time":0.3294734231},
{"learn":[0.01115579779],"iteration":265,"passed_time":0.3729625645,"remaining_time":0.3280948876},
{"learn":[0.01111608262],"iteration":266,"passed_time":0.374304087,"remaining_time":0.3266398961},
{"learn":[0.01102758686],"iteration":267,"passed_time":0.3756927722,"remaining_time":0.3252265789},
{"learn":[0.0109422711],"iteration":268,"passed_time":0.3770886662,"remaining_time":0.3238196353},
{"learn":[0.01089617422],"iteration":269,"passed_time":0.3785132248,"remaining_time":0.3224371915},
{"learn":[0.01083043101],"iteration":270,"passed_time":0.380058989,"remaining_time":0.3211568578},
{"learn":[0.01074182584],"iteration":271,"passed_time":0.3816552245,"remaining_time":0.3199168794},
{"learn":[0.01067449577],"iteration":272,"passed_time":0.3832209,"remaining_time":0.3186488802},
{"learn":[0.01063152148],"iteration":273,"passed_time":0.3846036603,"remaining_time":0.3172278366},
{"learn":[0.01057859072],"iteration":274,"passed_time":0.385966769,"remaining_time":0.3157909928},
{"learn":[0.01054619015],"iteration":275,"passed_time":0.3873210246,"remaining_time":0.3143474982},
{"learn":[0.01051779237],"iteration":276,"passed_time":0.3887035538,"remaining_time":0.3129274097},
{"learn":[0.01048372744],"iteration":277,"passed_time":0.3900583007,"remaining_time":0.3114854056},
{"learn":[0.01042476293],"iteration":278,"passed_time":0.3914137293,"remaining_time":0.310044567},
{"learn":[0.01039601568],"iteration":279,"passed_time":0.3926959273,"remaining_time":0.3085468001},
{"learn":[0.01037626111],"iteration":280,"passed_time":0.3941133273,"remaining_time":0.3071559384},
{"learn":[0.01036014972],"iteration":281,"passed_time":0.3955957861,"remaining_time":0.3058151822},
{"learn":[0.01031084127],"iteration":282,"passed_time":0.3969675874,"remaining_time":0.3043885741},
{"learn":[0.01027659877],"iteration":283,"passed_time":0.3983406419,"remaining_time":0.3029633051},
{"learn":[0.01023131531],"iteration":284,"passed_time":0.3996827259,"remaining_time":0.3015150388},
{"learn":[0.01017207147],"iteration":285,"passed_time":0.401047549,"remaining_time":0.3000845296},
{"learn":[0.01013226103],"iteration":286,"passed_time":0.4023744534,"remaining_time":0.2986263365},
{"learn":[0.01011919381],"iteration":287,"passed_time":0.4036559897,"remaining_time":0.297135659},
{"learn":[0.0100874787],"iteration":288,"passed_time":0.4049811896,"remaining_time":0.295678308},
{"learn":[0.0100535824],"iteration":289,"passed_time":0.4063138791,"remaining_time":0.2942272917},
{"learn":[0.010045958],"iteration":290,"passed_time":0.4075680647,"remaining_time":0.2927207063},
{"learn":[0.01002149149],"iteration":291,"passed_time":0.4089184402,"remaining_time":0.2912843684},
{"learn":[0.00994032949],"iteration":292,"passed_time":0.4103588,"remaining_time":0.2899121897},
{"learn":[0.009913203304],"iteration":293,"passed_time":0.411654834,"remaining_time":0.2884384211},
{"learn":[0.009831464931],"iteration":294,"passed_time":0.4129690253,"remaining_time":0.2869784752},
{"learn":[0.009797906999],"iteration":295,"passed_time":0.4142752458,"remaining_time":0.2855140208},
{"learn":[0.00979164828],"iteration":296,"passed_time":0.4155517189,"remaining_time":0.2840302995},
{"learn":[0.009755854882],"iteration":297,"passed_time":0.4168851002,"remaining_time":0.2825865444},
{"learn":[0.009734597678],"iteration":298,"passed_time":0.4182107714,"remaining_time":0.2811383446},
{"learn":[0.009705444325],"iteration":299,"passed_time":0.4195190072,"remaining_time":0.2796793381},
{"learn":[0.009695957691],"iteration":300,"passed_time":0.4208430341,"remaining_time":0.2782317734},
{"learn":[0.009679947884],"iteration":301,"passed_time":0.4221949937,"remaining_time":0.2768033402},
{"learn":[0.009617958616],"iteration":302,"passed_time":0.4235689005,"remaining_time":0.2753896812},
{"learn":[0.009576360582],"iteration":303,"passed_time":0.4250435294,"remaining_time":0.2740412229},
{"learn":[0.009563753202],"iteration":304,"passed_time":0.426362814,"remaining_time":0.2725926188},
{"learn":[0.00948171031],"iteration":305,"passed_time":0.4277198769,"remaining_time":0.2711688108},
{"learn":[0.009466288417],"iteration":306,"passed_time":0.4290004507,"remaining_time":0.2696973517},
{"learn":[0.009456219681],"iteration":307,"passed_time":0.4302909503,"remaining_time":0.2682333197},
{"learn":[0.00944037547],"iteration":308,"passed_time":0.4316150875,"remaining_time":0.266791203},
{"learn":[0.009386606399],"iteration":309,"passed_time":0.4329364775,"remaining_time":0.2653481637},
{"learn":[0.009350381881],"iteration":310,"passed_time":0.4342346872,"remaining_time":0.2638918196},
{"learn":[0.009305359948],"iteration":311,"passed_time":0.4356005731,"remaining_time":0.2624772684},
{"learn":[0.009272060215],"iteration":312,"passed_time":0.4369256327,"remaining_time":0.2610386368},
{"learn":[0.009248437025],"iteration":313,"passed_time":0.4381930121,"remaining_time":0.2595665613},
{"learn":[0.009243604709],"iteration":314,"passed_time":0.4394852663,"remaining_time":0.2581103945},
{"learn":[0.009202592971],"iteration":315,"passed_time":0.4410369559,"remaining_time":0.2568063288},
{"learn":[0.009183182571],"iteration":316,"passed_time":0.4423792715,"remaining_time":0.2553798318},
{"learn":[0.009158494637],"iteration":317,"passed_time":0.4436675242,"remaining_time":0.2539229227},
{"learn":[0.009131316516],"iteration":318,"passed_time":0.444981144,"remaining_time":0.2524814642},
{"learn":[0.009096376774],"iteration":319,"passed_time":0.4463150867,"remaining_time":0.2510522363},
{"learn":[0.009048148173],"iteration":320,"passed_time":0.4476593563,"remaining_time":0.2496293607},
{"learn":[0.009012537121],"iteration":321,"passed_time":0.4489839948,"remaining_time":0.2481961214},
{"learn":[0.008979994889],"iteration":322,"passed_time":0.4502999106,"remaining_time":0.2467587745},
{"learn":[0.008940745622],"iteration":323,"passed_time":0.4516589587,"remaining_time":0.2453456072},
{"learn":[0.008930598431],"iteration":324,"passed_time":0.4529458389,"remaining_time":0.2438939132},
{"learn":[0.008884475916],"iteration":325,"passed_time":0.454335617,"remaining_time":0.2424981514},
{"learn":[0.00886921976],"iteration":326,"passed_time":0.4557944442,"remaining_time":0.2411389567},
{"learn":[0.00882636077],"iteration":327,"passed_time":0.4573462146,"remaining_time":0.239827893},
{"learn":[0.008795154889],"iteration":328,"passed_time":0.4588802883,"remaining_time":0.2385061681},
{"learn":[0.008763355204],"iteration":329,"passed_time":0.4603123559,"remaining_time":0.2371306076},
{"learn":[0.008756581756],"iteration":330,"passed_time":0.4616077684,"remaining_time":0.2356849331},
{"learn":[0.0087199303],"iteration":331,"passed_time":0.4630715496,"remaining_time":0.2343253625},
{"learn":[0.008714923563],"iteration":332,"passed_time":0.46439307,"remaining_time":0.2328938219},
{"learn":[0.00869055398],"iteration":333,"passed_time":0.4657713281,"remaining_time":0.2314911391},
{"learn":[0.008645903754],"iteration":334,"passed_time":0.4671606249,"remaining_time":0.2300940391},
{"learn":[0.008618744863],"iteration":335,"passed_time":0.4685307719,"remaining_time":0.2286876387},
{"learn":[0.008581063336],"iteration":336,"passed_time":0.4699229763,"remaining_time":0.2272921221},
{"learn":[0.008573478164],"iteration":337,"passed_time":0.4713696124,"remaining_time":0.2259227136},
{"learn":[0.008534952925],"iteration":338,"passed_time":0.4727725648,"remaining_time":0.224532103},
{"learn":[0.008509675507],"iteration":339,"passed_time":0.4741526276,"remaining_time":0.2231306483},
{"learn":[0.00846983649],"iteration":340,"passed_time":0.4755119463,"remaining_time":0.2217196465},
{"learn":[0.008415926981],"iteration":341,"passed_time":0.4768760877,"remaining_time":0.220311175},
{"learn":[0.008382257677],"iteration":342,"passed_time":0.4782283782,"remaining_time":0.2188975375},
{"learn":[0.00832976368],"iteration":343,"passed_time":0.4796186876,"remaining_time":0.2175014979},
{"learn":[0.008285301489],"iteration":344,"passed_time":0.4809274949,"remaining_time":0.2160688745},
{"learn":[0.008248782893],"iteration":345,"passed_time":0.4822746721,"remaining_time":0.2146540448},
{"learn":[0.008196109096],"iteration":346,"passed_time":0.4836005137,"remaining_time":0.2132301977},
{"learn":[0.008141678172],"iteration":347,"passed_time":0.4849349277,"remaining_time":0.2118106581},
{"learn":[0.008131610901],"iteration":348,"passed_time":0.486302137,"remaining_time":0.2104057957},
{"learn":[0.008105518064],"iteration":349,"passed_time":0.4876242389,"remaining_time":0.2089818167},
{"learn":[0.008084935526],"iteration":350,"passed_time":0.4889566576,"remaining_time":0.2075627977},
{"learn":[0.008052293613],"iteration":351,"passed_time":0.4903017594,"remaining_time":0.2061496034},
{"learn":[0.008022142426],"iteration":352,"passed_time":0.4916252148,"remaining_time":0.2047277807},
{"learn":[0.007998240254],"iteration":353,"passed_time":0.4929467051,"remaining_time":0.2033057032},
{"learn":[0.007981072202],"iteration":354,"passed_time":0.4942485442,"remaining_time":0.201876166},
{"learn":[0.007950152198],"iteration":355,"passed_time":0.4956305521,"remaining_time":0.2004797739},
{"learn":[0.007921584527],"iteration":356,"passed_time":0.4969721648,"remaining_time":0.1990672817},
{"learn":[0.007883546167],"iteration":357,"passed_time":0.4983537816,"remaining_time":0.197671053},
{"learn":[0.007848540729],"iteration":358,"passed_time":0.4997175821,"remaining_time":0.1962679083},
{"learn":[0.007804510908],"iteration":359,"passed_time":0.501035874,"remaining_time":0.1948472843},
{"learn":[0.007759765342],"iteration":360,"passed_time":0.5024639418,"remaining_time":0.1934694956},
{"learn":[0.007741463684],"iteration":361,"passed_time":0.5037810908,"remaining_time":0.1920491451},
{"learn":[0.007710373003],"iteration":362,"passed_time":0.5051466258,"remaining_time":0.1906476246},
{"learn":[0.007691294026],"iteration":363,"passed_time":0.5064955475,"remaining_time":0.1892400947},
{"learn":[0.007682187431],"iteration":364,"passed_time":0.5078509661,"remaining_time":0.1878352888},
{"learn":[0.007645046388],"iteration":365,"passed_time":0.5092507703,"remaining_time":0.1864470033},
{"learn":[0.007620515858],"iteration":366,"passed_time":0.510611212,"remaining_time":0.1850443902},
{"learn":[0.007598194593],"iteration":367,"passed_time":0.5119885276,"remaining_time":0.1836480588},
{"learn":[0.007593349514],"iteration":368,"passed_time":0.5132972046,"remaining_time":0.1822274629},
{"learn":[0.007573023746],"iteration":369,"passed_time":0.5146405919,"remaining_time":0.1808196674},
{"learn":[0.007523944711],"iteration":370,"passed_time":0.5159901352,"remaining_time":0.1794143597},
{"learn":[0.007510216353],"iteration":371,"passed_time":0.5173512587,"remaining_time":0.1780133363},
{"learn":[0.00747591723],"iteration":372,"passed_time":0.5187128133,"remaining_time":0.1766126737},
{"learn":[0.007452995538],"iteration":373,"passed_time":0.5200493026,"remaining_time":0.1752037758},
{"learn":[0.007404623827],"iteration":374,"passed_time":0.5213978534,"remaining_time":0.1737992845},
{"learn":[0.007400618438],"iteration":375,"passed_time":0.5226706369,"remaining_time":0.1723701037},
{"learn":[0.007366833863],"iteration":376,"passed_time":0.5239951049,"remaining_time":0.1709586151},
{"learn":[0.007362643118],"iteration":377,"passed_time":0.5253139584,"remaining_time":0.1695457749},
{"learn":[0.007344535076],"iteration":378,"passed_time":0.5266573457,"remaining_time":0.1681412634},
{"learn":[0.007338622961],"iteration":379,"passed_time":0.5279982365,"remaining_time":0.1667362852},
{"learn":[0.007314753367],"iteration":380,"passed_time":0.529349374,"remaining_time":0.1653348438},
{"learn":[0.007308720225],"iteration":381,"passed_time":0.5306236112,"remaining_time":0.1639099113},
{"learn":[0.007287835879],"iteration":382,"passed_time":0.5320792508,"remaining_time":0.162541181},
{"learn":[0.007259552547],"iteration":383,"passed_time":0.5334368952,"remaining_time":0.1611423954},
{"learn":[0.007244332468],"iteration":384,"passed_time":0.5347788187,"remaining_time":0.1597391277},
{"learn":[0.007225977826],"iteration":385,"passed_time":0.5360975618,"remaining_time":0.1583293317},
{"learn":[0.007213635042],"iteration":386,"passed_time":0.5374037523,"remaining_time":0.1569163411},
{"learn":[0.007201525186],"iteration":387,"passed_time":0.5387176529,"remaining_time":0.1555061266},
{"learn":[0.007183761619],"iteration":388,"passed_time":0.5399875188,"remaining_time":0.1540838421},
{"learn":[0.007156099742],"iteration":389,"passed_time":0.5413086782,"remaining_time":0.1526768067},
{"learn":[0.007140054781],"iteration":390,"passed_time":0.5426221276,"remaining_time":0.1512680611},
{"learn":[0.007127777706],"iteration":391,"passed_time":0.543925992,"remaining_time":0.1498571611},
{"learn":[0.007109897397],"iteration":392,"passed_time":0.5453413617,"remaining_time":0.1484771646},
{"learn":[0.00709945189],"iteration":393,"passed_time":0.5470260776,"remaining_time":0.1471694523},
{"learn":[0.007067892095],"iteration":394,"passed_time":0.5484518895,"remaining_time":0.1457910086},
{"learn":[0.007046884527],"iteration":395,"passed_time":0.5498532678,"remaining_time":0.1444059087},
{"learn":[0.007018635515],"iteration":396,"passed_time":0.5512298515,"remaining_time":0.143014294},
{"learn":[0.007017247922],"iteration":397,"passed_time":0.5524774394,"remaining_time":0.1415896955},
{"learn":[0.006996533596],"iteration":398,"passed_time":0.5539333195,"remaining_time":0.14021871},
{"learn":[0.006971879806],"iteration":399,"passed_time":0.5552862918,"remaining_time":0.138821573},
{"learn":[0.00694326784],"iteration":400,"passed_time":0.5565753376,"remaining_time":0.1374088739},
{"learn":[0.006923452576],"iteration":401,"passed_time":0.5579177624,"remaining_time":0.1360098028},
{"learn":[0.006910517067],"iteration":402,"passed_time":0.5592423508,"remaining_time":0.1346067197},
{"learn":[0.00688789079],"iteration":403,"passed_time":0.5607399847,"remaining_time":0.1332451449},
{"learn":[0.006872711828],"iteration":404,"passed_time":0.5623499872,"remaining_time":0.1319092563},
{"learn":[0.006870624357],"iteration":405,"passed_time":0.5638049048,"remaining_time":0.130536111},
{"learn":[0.006868217225],"iteration":406,"passed_time":0.5651841043,"remaining_time":0.1291452622},
{"learn":[0.006850930021],"iteration":407,"passed_time":0.5665018949,"remaining_time":0.1277406234},
{"learn":[0.006836144874],"iteration":408,"passed_time":0.5678335116,"remaining_time":0.1263394855},
{"learn":[0.006817018628],"iteration":409,"passed_time":0.5691640555,"remaining_time":0.1249384512},
{"learn":[0.006807951236],"iteration":410,"passed_time":0.5704452709,"remaining_time":0.1235270781},
{"learn":[0.006795811434],"iteration":411,"passed_time":0.571762851,"remaining_time":0.1221241041},
{"learn":[0.006780794585],"iteration":412,"passed_time":0.5731452599,"remaining_time":0.1207352},
{"learn":[0.006757840811],"iteration":413,"passed_time":0.5744408328,"remaining_time":0.1193282889},
{"learn":[0.006748580931],"iteration":414,"passed_time":0.5759292175,"remaining_time":0.117961406},
{"learn":[0.006711469414],"iteration":415,"passed_time":0.5773636218,"remaining_time":0.116583039},
{"learn":[0.00667050782],"iteration":416,"passed_time":0.5787564077,"remaining_time":0.1151961195},
{"learn":[0.006644138479],"iteration":417,"passed_time":0.5801429574,"remaining_time":0.1138079486},
{"learn":[0.006627887204],"iteration":418,"passed_time":0.5815461203,"remaining_time":0.112422997},
{"learn":[0.006605976596],"iteration":419,"passed_time":0.5829356979,"remaining_time":0.111035371},
{"learn":[0.006566889428],"iteration":420,"passed_time":0.5843919083,"remaining_time":0.1096602393},
{"learn":[0.006552682128],"iteration":421,"passed_time":0.5857578945,"remaining_time":0.1082680468},
{"learn":[0.006545418417],"iteration":422,"passed_time":0.5870700605,"remaining_time":0.1068661812},
{"learn":[0.006524351525],"iteration":423,"passed_time":0.5884595679,"remaining_time":0.1054786018},
{"learn":[0.006499070504],"iteration":424,"passed_time":0.5899504692,"remaining_time":0.1041089063},
{"learn":[0.00648049375],"iteration":425,"passed_time":0.5913549857,"remaining_time":0.102723636},
{"learn":[0.006470370251],"iteration":426,"passed_time":0.592716069,"remaining_time":0.1013308502},
{"learn":[0.00644426524],"iteration":427,"passed_time":0.5941590255,"remaining_time":0.09995198561},
{"learn":[0.006423346866],"iteration":428,"passed_time":0.595526285,"remaining_time":0.09856029425},
{"learn":[0.00640708506],"iteration":429,"passed_time":0.5969461915,"remaining_time":0.09717728699},
{"learn":[0.00638969712],"iteration":430,"passed_time":0.598285819,"remaining_time":0.09578125641},
{"learn":[0.006375704629],"iteration":431,"passed_time":0.5996610492,"remaining_time":0.09439109108},
{"learn":[0.006351289719],"iteration":432,"passed_time":0.601022664,"remaining_time":0.09299888796},
{"learn":[0.00632024549],"iteration":433,"passed_time":0.6024424301,"remaining_time":0.0916156691},
{"learn":[0.006318486022],"iteration":434,"passed_time":0.6036505152,"remaining_time":0.0902006517},
{"learn":[0.00630185768],"iteration":435,"passed_time":0.6050695896,"remaining_time":0.08881755443},
{"learn":[0.006281727046],"iteration":436,"passed_time":0.6064998631,"remaining_time":0.08743590703},
{"learn":[0.00628070648],"iteration":437,"passed_time":0.607815067,"remaining_time":0.08603774921},
{"learn":[0.006278706939],"iteration":438,"passed_time":0.6091414801,"remaining_time":0.08464152685},
{"learn":[0.006265639478],"iteration":439,"passed_time":0.6104898704,"remaining_time":0.0832486187},
{"learn":[0.00624244623],"iteration":440,"passed_time":0.6118562977,"remaining_time":0.08185832555},
{"learn":[0.00622762872],"iteration":441,"passed_time":0.613207375,"remaining_time":0.08046612614},
{"learn":[0.00622665707],"iteration":442,"passed_time":0.614431532,"remaining_time":0.07905778176},
{"learn":[0.00619560918],"iteration":443,"passed_time":0.6158557296,"remaining_time":0.07767549743},
{"learn":[0.006188070935],"iteration":444,"passed_time":0.6171790748,"remaining_time":0.0762805598},
{"learn":[0.006161203658],"iteration":445,"passed_time":0.61853702,"remaining_time":0.07489013246},
{"learn":[0.006155066478],"iteration":446,"passed_time":0.619813453,"remaining_time":0.0734901857},
{"learn":[0.006134611923],"iteration":447,"passed_time":0.6213206868,"remaining_time":0.07211757972},
{"learn":[0.006122919365],"iteration":448,"passed_time":0.6226165504,"remaining_time":0.07072036541},
{"learn":[0.006104123477],"iteration":449,"passed_time":0.6239830379,"remaining_time":0.06933144865},
{"learn":[0.006088768904],"iteration":450,"passed_time":0.6253426073,"remaining_time":0.06794187973},
{"learn":[0.006067031373],"iteration":451,"passed_time":0.6267217878,"remaining_time":0.06655452614},
{"learn":[0.006055146147],"iteration":452,"passed_time":0.6280172002,"remaining_time":0.06515851746},
{"learn":[0.006024027484],"iteration":453,"passed_time":0.6293353217,"remaining_time":0.06376525286},
{"learn":[0.006003390007],"iteration":454,"passed_time":0.6307368504,"remaining_time":0.06238056762},
{"learn":[0.005996145743],"iteration":455,"passed_time":0.632121665,"remaining_time":0.06099419574},
{"learn":[0.005978796697],"iteration":456,"passed_time":0.6334990213,"remaining_time":0.05960712892},
{"learn":[0.005947835352],"iteration":457,"passed_time":0.6348430803,"remaining_time":0.05821705104},
{"learn":[0.005943683641],"iteration":458,"passed_time":0.63629491,"remaining_time":0.05683680024},
{"learn":[0.005943660685],"iteration":459,"passed_time":0.63754714,"remaining_time":0.05543888173},
{"learn":[0.005922128784],"iteration":460,"passed_time":0.6389973453,"remaining_time":0.05405834375},
{"learn":[0.005911611981],"iteration":461,"passed_time":0.6403551903,"remaining_time":0.05266990743},
{"learn":[0.005891993024],"iteration":462,"passed_time":0.6417028988,"remaining_time":0.05128079321},
{"learn":[0.005884227008],"iteration":463,"passed_time":0.6430202584,"remaining_time":0.04988950281},
{"learn":[0.005875030924],"iteration":464,"passed_time":0.6443367056,"remaining_time":0.04849846171},
{"learn":[0.00586523343],"iteration":465,"passed_time":0.645623305,"remaining_time":0.04710556303},
{"learn":[0.005865181616],"iteration":466,"passed_time":0.6467466495,"remaining_time":0.04570158337},
{"learn":[0.0058477997],"iteration":467,"passed_time":0.6480691925,"remaining_time":0.04431242342},
{"learn":[0.005829398943],"iteration":468,"passed_time":0.649394984,"remaining_time":0.04292376227},
{"learn":[0.005807804077],"iteration":469,"passed_time":0.6510714384,"remaining_time":0.04155775139},
{"learn":[0.005797283016],"iteration":470,"passed_time":0.6525551911,"remaining_time":0.04017855742},
{"learn":[0.005776729397],"iteration":471,"passed_time":0.6540266118,"remaining_time":0.03879818883},
{"learn":[0.005761791994],"iteration":472,"passed_time":0.6555618184,"remaining_time":0.03742107632},
{"learn":[0.005751924552],"iteration":473,"passed_time":0.6569818754,"remaining_time":0.0360369805},
{"learn":[0.005724675687],"iteration":474,"passed_time":0.6583130308,"remaining_time":0.03464805425},
{"learn":[0.005709456347],"iteration":475,"passed_time":0.6596268311,"remaining_time":0.03325849569},
{"learn":[0.005694889575],"iteration":476,"passed_time":0.6609557908,"remaining_time":0.03186998572},
{"learn":[0.005690698635],"iteration":477,"passed_time":0.6623857034,"remaining_time":0.03048637129},
{"learn":[0.005661132151],"iteration":478,"passed_time":0.6637459346,"remaining_time":0.02909950861},
{"learn":[0.005643624929],"iteration":479,"passed_time":0.6652016242,"remaining_time":0.02771673434},
{"learn":[0.005627648222],"iteration":480,"passed_time":0.6665241472,"remaining_time":0.02632839667},
{"learn":[0.005627663692],"iteration":481,"passed_time":0.6676386587,"remaining_time":0.02493256402},
{"learn":[0.005599318403],"iteration":482,"passed_time":0.6690509047,"remaining_time":0.02354837553},
{"learn":[0.005586513916],"iteration":483,"passed_time":0.6704068848,"remaining_time":0.02216221107},
{"learn":[0.005564767032],"iteration":484,"passed_time":0.6717377996,"remaining_time":0.02077539586},
{"learn":[0.005545494503],"iteration":485,"passed_time":0.673121713,"remaining_time":0.01939033741},
{"learn":[0.005537986089],"iteration":486,"passed_time":0.6745020866,"remaining_time":0.01800518917},
{"learn":[0.005512448146],"iteration":487,"passed_time":0.675899304,"remaining_time":0.01662047469},
{"learn":[0.00549434047],"iteration":488,"passed_time":0.6772766197,"remaining_time":0.01523526138},
{"learn":[0.005480896086],"iteration":489,"passed_time":0.6786591689,"remaining_time":0.01385018712},
{"learn":[0.005463480441],"iteration":490,"passed_time":0.6802311263,"remaining_time":0.01246859498},
{"learn":[0.005453911899],"iteration":491,"passed_time":0.681717937,"remaining_time":0.0110848445},
{"learn":[0.005453911899],"iteration":492,"passed_time":0.6828008862,"remaining_time":0.00969494159},
{"learn":[0.005451133275],"iteration":493,"passed_time":0.6840485243,"remaining_time":0.008308281671},
{"learn":[0.005436572726],"iteration":494,"passed_time":0.6854156835,"remaining_time":0.006923390742},
{"learn":[0.005426912417],"iteration":495,"passed_time":0.6867419763,"remaining_time":0.005538241744},
{"learn":[0.005416684813],"iteration":496,"passed_time":0.6880986381,"remaining_time":0.004153512906},
{"learn":[0.005408167196],"iteration":497,"passed_time":0.6894039062,"remaining_time":0.002768690386},
{"learn":[0.005389188851],"iteration":498,"passed_time":0.6907500908,"remaining_time":0.001384268719},
{"learn":[0.005375270543],"iteration":499,"passed_time":0.6920845749,"remaining_time":0}
]}