{
"meta":{"test_sets":[],"test_metrics":[],"learn_metrics":[{"best_value":"Min","name":"Logloss"}],"launch_mode":"Train","parameters":"","iteration_count":1000,"learn_sets":["learn"],"name":"experiment"},
"iterations":[
{"learn":[0.5613839164],"iteration":0,"passed_time":0.1429103493,"remaining_time":142.7674389},
{"learn":[0.4463959678],"iteration":1,"passed_time":0.1449241683,"remaining_time":72.31716},
{"learn":[0.4035760671],"iteration":2,"passed_time":0.1469450756,"remaining_time":48.8347468},
{"learn":[0.3798611716],"iteration":3,"passed_time":0.148884285,"remaining_time":37.07218697},
{"learn":[0.3588824284],"iteration":4,"passed_time":0.1508383483,"remaining_time":30.01683132},
{"learn":[0.3377413083],"iteration":5,"passed_time":0.1527469794,"remaining_time":25.30508292},
{"learn":[0.3273058322],"iteration":6,"passed_time":0.1545663445,"remaining_time":21.92634001},
{"learn":[0.3185901331],"iteration":7,"passed_time":0.1564218372,"remaining_time":19.39630782},
{"learn":[0.3102269027],"iteration":8,"passed_time":0.1582374253,"remaining_time":17.42369871},
{"learn":[0.3010510007],"iteration":9,"passed_time":0.1600945961,"remaining_time":15.84936502},
{"learn":[0.2967374239],"iteration":10,"passed_time":0.1615904507,"remaining_time":14.52845053},
{"learn":[0.2897392693],"iteration":11,"passed_time":0.1629345463,"remaining_time":13.41494431},
{"learn":[0.2860160001],"iteration":12,"passed_time":0.1642511004,"remaining_time":12.47044893},
{"learn":[0.2711419698],"iteration":13,"passed_time":0.1656455152,"remaining_time":11.666177},
{"learn":[0.2684530596],"iteration":14,"passed_time":0.1669912739,"remaining_time":10.96576032},
{"learn":[0.2630057254],"iteration":15,"passed_time":0.168372544,"remaining_time":10.35491146},
{"learn":[0.2506390754],"iteration":16,"passed_time":0.1698070989,"remaining_time":9.818845779},
{"learn":[0.2428563557],"iteration":17,"passed_time":0.1712785429,"remaining_time":9.34419606},
{"learn":[0.2379309085],"iteration":18,"passed_time":0.1726408024,"remaining_time":8.913717221},
{"learn":[0.230779642],"iteration":19,"passed_time":0.1740085723,"remaining_time":8.526420045},
{"learn":[0.2246149242],"iteration":20,"passed_time":0.1753839465,"remaining_time":8.176232553},
{"learn":[0.2181925481],"iteration":21,"passed_time":0.1767449938,"remaining_time":7.857118361},
{"learn":[0.2093090915],"iteration":22,"passed_time":0.1781486859,"remaining_time":7.567446355},
{"learn":[0.2059735226],"iteration":23,"passed_time":0.1794801529,"remaining_time":7.298859551},
{"learn":[0.1997805902],"iteration":24,"passed_time":0.1808856734,"remaining_time":7.054541264},
{"learn":[0.1955204152],"iteration":25,"passed_time":0.1822819768,"remaining_time":6.828563283},
{"learn":[0.1924848474],"iteration":26,"passed_time":0.1836257217,"remaining_time":6.617326933},
{"learn":[0.1881475186],"iteration":27,"passed_time":0.1850394175,"remaining_time":6.423511209},
{"learn":[0.1849602674],"iteration":28,"passed_time":0.1864111198,"remaining_time":6.241558529},
{"learn":[0.1796108187],"iteration":29,"passed_time":0.1878330411,"remaining_time":6.073268327},
{"learn":[0.175659133],"iteration":30,"passed_time":0.1892944913,"remaining_time":5.916979421},
{"learn":[0.1705602079],"iteration":31,"passed_time":0.1906769837,"remaining_time":5.767978758},
{"learn":[0.1677872684],"iteration":32,"passed_time":0.1920451594,"remaining_time":5.627505126},
{"learn":[0.1643814267],"iteration":33,"passed_time":0.1934126388,"remaining_time":5.495194384},
{"learn":[0.1584314017],"iteration":34,"passed_time":0.1947954668,"remaining_time":5.3707893},
{"learn":[0.1552898291],"iteration":35,"passed_time":0.1961816412,"remaining_time":5.253308392},
{"learn":[0.151774952],"iteration":36,"passed_time":0.1975952018,"remaining_time":5.142815658},
{"learn":[0.1492326263],"iteration":37,"passed_time":0.198982904,"remaining_time":5.037409307},
{"learn":[0.1466519394],"iteration":38,"passed_time":0.2003816719,"remaining_time":4.937609916},
{"learn":[0.1432399269],"iteration":39,"passed_time":0.2018447051,"remaining_time":4.844272923},
{"learn":[0.139802391],"iteration":40,"passed_time":0.2034423603,"remaining_time":4.758566427},
{"learn":[0.1373136143],"iteration":41,"passed_time":0.2049284516,"remaining_time":4.674320396},
{"learn":[0.1338616965],"iteration":42,"passed_time":0.2064082813,"remaining_time":4.593784306},
{"learn":[0.1309124861],"iteration":43,"passed_time":0.2078409626,"remaining_time":4.515817279},
{"learn":[0.1280091559],"iteration":44,"passed_time":0.209233559,"remaining_time":4.440401086},
{"learn":[0.1251474284],"iteration":45,"passed_time":0.2106877507,"remaining_time":4.369480742},
{"learn":[0.1223028239],"iteration":46,"passed_time":0.2120820202,"remaining_time":4.300301387},
{"learn":[0.1196720203],"iteration":47,"passed_time":0.2134847655,"remaining_time":4.234114516},
{"learn":[0.1179336239],"iteration":48,"passed_time":0.214882211,"remaining_time":4.170469033},
{"learn":[0.1159051104],"iteration":49,"passed_time":0.2162815049,"remaining_time":4.109348592},
{"learn":[0.1140679411],"iteration":50,"passed_time":0.2176830129,"remaining_time":4.050611358},
{"learn":[0.1125694022],"iteration":51,"passed_time":0.2191052347,"remaining_time":3.994456971},
{"learn":[0.1117219853],"iteration":52,"passed_time":0.2204654004,"remaining_time":3.939259135},
{"learn":[0.1090632674],"iteration":53,"passed_time":0.2218608922,"remaining_time":3.886674148},
{"learn":[0.106732992],"iteration":54,"passed_time":0.223325348,"remaining_time":3.837135525},
{"learn":[0.1024991835],"iteration":55,"passed_time":0.2247739141,"remaining_time":3.789045981},
{"learn":[0.1001440824],"iteration":56,"passed_time":0.2262129625,"remaining_time":3.742435502},
{"learn":[0.09738758545],"iteration":57,"passed_time":0.2276071919,"remaining_time":3.696654737},
{"learn":[0.09448291744],"iteration":58,"passed_time":0.2290260274,"remaining_time":3.652771046},
{"learn":[0.09274484721],"iteration":59,"passed_time":0.2304220251,"remaining_time":3.60994506},
{"learn":[0.09032580809],"iteration":60,"passed_time":0.2318372738,"remaining_time":3.568773773},
{"learn":[0.08929045396],"iteration":61,"passed_time":0.2333059376,"remaining_time":3.529693056},
{"learn":[0.08699691247],"iteration":62,"passed_time":0.2348710869,"remaining_time":3.493241404},
{"learn":[0.08575535529],"iteration":63,"passed_time":0.2363613934,"remaining_time":3.456785378},
{"learn":[0.08352459053],"iteration":64,"passed_time":0.237781371,"remaining_time":3.420393567},
{"learn":[0.0820386992],"iteration":65,"passed_time":0.2391689479,"remaining_time":3.384602991},
{"learn":[0.08171776097],"iteration":66,"passed_time":0.2404755061,"remaining_time":3.348711152},
{"learn":[0.08085194964],"iteration":67,"passed_time":0.2418786422,"remaining_time":3.315160213},
{"learn":[0.07961608054],"iteration":68,"passed_time":0.2432879298,"remaining_time":3.282624096},
{"learn":[0.07847374014],"iteration":69,"passed_time":0.2447218106,"remaining_time":3.251304055},
{"learn":[0.07743907074],"iteration":70,"passed_time":0.2461325237,"remaining_time":3.220522739},
{"learn":[0.07569762513],"iteration":71,"passed_time":0.2478178223,"remaining_time":3.194096376},
{"learn":[0.07444597855],"iteration":72,"passed_time":0.249304197,"remaining_time":3.165821789},
{"learn":[0.07361326938],"iteration":73,"passed_time":0.2506779052,"remaining_time":3.136861354},
{"learn":[0.07245039081],"iteration":74,"passed_time":0.2520829148,"remaining_time":3.109022616},
{"learn":[0.07020224583],"iteration":75,"passed_time":0.2534857102,"remaining_time":3.081852582},
{"learn":[0.06974326133],"iteration":76,"passed_time":0.2548532197,"remaining_time":3.054928854},
{"learn":[0.06837095211],"iteration":77,"passed_time":0.2562284135,"remaining_time":3.028751246},
{"learn":[0.06645785342],"iteration":78,"passed_time":0.2576347956,"remaining_time":3.003565149},
{"learn":[0.0656455892],"iteration":79,"passed_time":0.259024216,"remaining_time":2.978778485},
{"learn":[0.06348286032],"iteration":80,"passed_time":0.2603946437,"remaining_time":2.954354044},
{"learn":[0.06194366119],"iteration":81,"passed_time":0.2617753651,"remaining_time":2.930607136},
{"learn":[0.06122302118],"iteration":82,"passed_time":0.263132976,"remaining_time":2.907143843},
{"learn":[0.05992111455],"iteration":83,"passed_time":0.2645802446,"remaining_time":2.885184573},
{"learn":[0.05891456861],"iteration":84,"passed_time":0.2659381132,"remaining_time":2.862745572},
{"learn":[0.05768601716],"iteration":85,"passed_time":0.2673547646,"remaining_time":2.841421568},
{"learn":[0.05688805553],"iteration":86,"passed_time":0.2687568588,"remaining_time":2.820402437},
{"learn":[0.05596459415],"iteration":87,"passed_time":0.2701619986,"remaining_time":2.799860713},
{"learn":[0.05477586041],"iteration":88,"passed_time":0.2715624397,"remaining_time":2.779700927},
{"learn":[0.05347701349],"iteration":89,"passed_time":0.2729873493,"remaining_time":2.76020542},
{"learn":[0.05260261337],"iteration":90,"passed_time":0.2743200708,"remaining_time":2.740186202},
{"learn":[0.05173760431],"iteration":91,"passed_time":0.2757368953,"remaining_time":2.721403271},
{"learn":[0.05110350118],"iteration":92,"passed_time":0.27715531,"remaining_time":2.703009313},
{"learn":[0.05008346816],"iteration":93,"passed_time":0.2786817541,"remaining_time":2.686017757},
{"learn":[0.04873069537],"iteration":94,"passed_time":0.2800566473,"remaining_time":2.667908061},
{"learn":[0.04826176251],"iteration":95,"passed_time":0.2814043897,"remaining_time":2.649891337},
{"learn":[0.04725028227],"iteration":96,"passed_time":0.282819471,"remaining_time":2.632845178},
{"learn":[0.04593580905],"iteration":97,"passed_time":0.2842239067,"remaining_time":2.616020039},
{"learn":[0.04556640241],"iteration":98,"passed_time":0.2855886409,"remaining_time":2.599145106},
{"learn":[0.04470812003],"iteration":99,"passed_time":0.2869684734,"remaining_time":2.582716261},
{"learn":[0.0441324927],"iteration":100,"passed_time":0.2883838524,"remaining_time":2.566901815},
{"learn":[0.04352685123],"iteration":101,"passed_time":0.2898082182,"remaining_time":2.551448823},
{"learn":[0.0426845682],"iteration":102,"passed_time":0.2912212929,"remaining_time":2.536169901},
{"learn":[0.04212910233],"iteration":103,"passed_time":0.2926171254,"remaining_time":2.52100908},
{"learn":[0.04168449181],"iteration":104,"passed_time":0.2940706858,"remaining_time":2.506602512},
{"learn":[0.04115982236],"iteration":105,"passed_time":0.2954472722,"remaining_time":2.491791145},
{"learn":[0.0400274418],"iteration":106,"passed_time":0.2968290083,"remaining_time":2.477273873},
{"learn":[0.03933232106],"iteration":107,"passed_time":0.2981921595,"remaining_time":2.462846355},
{"learn":[0.0385954221],"iteration":108,"passed_time":0.2995964377,"remaining_time":2.448994734},
{"learn":[0.03832361483],"iteration":109,"passed_time":0.3009561726,"remaining_time":2.435009033},
{"learn":[0.03770718544],"iteration":110,"passed_time":0.3023378085,"remaining_time":2.421426232},
{"learn":[0.03740708773],"iteration":111,"passed_time":0.3037353541,"remaining_time":2.40818745},
{"learn":[0.03635706132],"iteration":112,"passed_time":0.3051683461,"remaining_time":2.395436486},
{"learn":[0.03574363774],"iteration":113,"passed_time":0.3065076226,"remaining_time":2.382155734},
{"learn":[0.03530906987],"iteration":114,"passed_time":0.3079248223,"remaining_time":2.369682328},
{"learn":[0.03484412992],"iteration":115,"passed_time":0.3093678057,"remaining_time":2.357596037},
{"learn":[0.0343076835],"iteration":116,"passed_time":0.3108109495,"remaining_time":2.345692892},
{"learn":[0.03375490513],"iteration":117,"passed_time":0.3122344737,"remaining_time":2.333820388},
{"learn":[0.03345153372],"iteration":118,"passed_time":0.3136336096,"remaining_time":2.321942941},
{"learn":[0.03293142662],"iteration":119,"passed_time":0.3150178403,"remaining_time":2.310130829},
{"learn":[0.03236948317],"iteration":120,"passed_time":0.3164099184,"remaining_time":2.298548085},
{"learn":[0.03191694008],"iteration":121,"passed_time":0.3177859911,"remaining_time":2.287017215},
{"learn":[0.03170362368],"iteration":122,"passed_time":0.3191679976,"remaining_time":2.275693772},
{"learn":[0.03109059904],"iteration":123,"passed_time":0.3205494532,"remaining_time":2.264526782},
{"learn":[0.03077765097],"iteration":124,"passed_time":0.3218966846,"remaining_time":2.253276792},
{"learn":[0.03040347094],"iteration":125,"passed_time":0.3233815336,"remaining_time":2.243138575},
{"learn":[0.03031059307],"iteration":126,"passed_time":0.3250523385,"remaining_time":2.234414894},
{"learn":[0.03019736176],"iteration":127,"passed_time":0.3264968515,"remaining_time":2.224259801},
{"learn":[0.02994418297],"iteration":128,"passed_time":0.3280539485,"remaining_time":2.214999916},
{"learn":[0.02991667726],"iteration":129,"passed_time":0.3294026928,"remaining_time":2.204464175},
{"learn":[0.02916962175],"iteration":130,"passed_time":0.3308102499,"remaining_time":2.194458833},
{"learn":[0.02877350108],"iteration":131,"passed_time":0.3322334608,"remaining_time":2.184686697},
{"learn":[0.0285464603],"iteration":132,"passed_time":0.3336405543,"remaining_time":2.174935042},
{"learn":[0.02826935636],"iteration":133,"passed_time":0.3350048505,"remaining_time":2.165031347},
{"learn":[0.02772686402],"iteration":134,"passed_time":0.3364364198,"remaining_time":2.155685208},
{"learn":[0.02744442921],"iteration":135,"passed_time":0.3379731459,"remaining_time":2.147123515},
{"learn":[0.02723709626],"iteration":136,"passed_time":0.3394813887,"remaining_time":2.138484952},
{"learn":[0.02700782775],"iteration":137,"passed_time":0.3408541953,"remaining_time":2.129103741},
{"learn":[0.0266489594],"iteration":138,"passed_time":0.3422737148,"remaining_time":2.120127111},
{"learn":[0.02624854432],"iteration":139,"passed_time":0.3436793728,"remaining_time":2.11117329},
{"learn":[0.02606260188],"iteration":140,"passed_time":0.3450328259,"remaining_time":2.102008493},
{"learn":[0.02562420738],"iteration":141,"passed_time":0.3463870505,"remaining_time":2.092958376},
{"learn":[0.02523092505],"iteration":142,"passed_time":0.347793072,"remaining_time":2.084326313},
{"learn":[0.02505764347],"iteration":143,"passed_time":0.3491825425,"remaining_time":2.075696225},
{"learn":[0.02477780491],"iteration":144,"passed_time":0.3505954569,"remaining_time":2.067304246},
{"learn":[0.02442616499],"iteration":145,"passed_time":0.3519711143,"remaining_time":2.058789943},
{"learn":[0.02424076796],"iteration":146,"passed_time":0.3534754671,"remaining_time":2.051119547},
{"learn":[0.02401992252],"iteration":147,"passed_time":0.3549030317,"remaining_time":2.043090426},
{"learn":[0.02377230528],"iteration":148,"passed_time":0.3563537941,"remaining_time":2.035282408},
{"learn":[0.02364339826],"iteration":149,"passed_time":0.3577039611,"remaining_time":2.026989113},
{"learn":[0.02326617323],"iteration":150,"passed_time":0.3590881818,"remaining_time":2.018979247},
{"learn":[0.02308562805],"iteration":151,"passed_time":0.3604563825,"remaining_time":2.010967187},
{"learn":[0.02263031089],"iteration":152,"passed_time":0.3618099658,"remaining_time":2.002961053},
{"learn":[0.02232725869],"iteration":153,"passed_time":0.3631726863,"remaining_time":1.99509151},
{"learn":[0.02206625301],"iteration":154,"passed_time":0.3645421995,"remaining_time":1.987342958},
{"learn":[0.021954896],"iteration":155,"passed_time":0.3659442635,"remaining_time":1.979852298},
{"learn":[0.02176480191],"iteration":156,"passed_time":0.367342265,"remaining_time":1.972417385},
{"learn":[0.02162957947],"iteration":157,"passed_time":0.36884898,"remaining_time":1.965638235},
{"learn":[0.02144709478],"iteration":158,"passed_time":0.370254087,"remaining_time":1.958387969},
{"learn":[0.02114078056],"iteration":159,"passed_time":0.3716086421,"remaining_time":1.950945371},
{"learn":[0.02083087157],"iteration":160,"passed_time":0.3730342202,"remaining_time":1.943948514},
{"learn":[0.02030344794],"iteration":161,"passed_time":0.3744231898,"remaining_time":1.936831068},
{"learn":[0.02028952309],"iteration":162,"passed_time":0.3757540005,"remaining_time":1.929485267},
{"learn":[0.0199745754],"iteration":163,"passed_time":0.3771866819,"remaining_time":1.92273211},
{"learn":[0.01960166902],"iteration":164,"passed_time":0.3785722552,"remaining_time":1.915805049},
{"learn":[0.01930597658],"iteration":165,"passed_time":0.3799420589,"remaining_time":1.908865525},
{"learn":[0.01911812263],"iteration":166,"passed_time":0.3812908332,"remaining_time":1.901887809},
{"learn":[0.01893398194],"iteration":167,"passed_time":0.3828477449,"remaining_time":1.896007879},
{"learn":[0.01871587971],"iteration":168,"passed_time":0.3843483156,"remaining_time":1.889902072},
{"learn":[0.01849954319],"iteration":169,"passed_time":0.3858605058,"remaining_time":1.883907175},
{"learn":[0.01830439084],"iteration":170,"passed_time":0.3873144469,"remaining_time":1.877682319},
{"learn":[0.01821868553],"iteration":171,"passed_time":0.3887522908,"remaining_time":1.871435446},
{"learn":[0.01798953348],"iteration":172,"passed_time":0.3901300594,"remaining_time":1.864956989},
{"learn":[0.0178653726],"iteration":173,"passed_time":0.3915497938,"remaining_time":1.858736377},
{"learn":[0.01777464547],"iteration":174,"passed_time":0.3929332831,"remaining_time":1.852399763},
{"learn":[0.01772173691],"iteration":175,"passed_time":0.3942962941,"remaining_time":1.846023559},
{"learn":[0.01746906783],"iteration":176,"passed_time":0.3956888404,"remaining_time":1.839841331},
{"learn":[0.01735903797],"iteration":177,"passed_time":0.3971252086,"remaining_time":1.833915289},
{"learn":[0.01715542677],"iteration":178,"passed_time":0.3985489533,"remaining_time":1.827981512},
{"learn":[0.01698396162],"iteration":179,"passed_time":0.3999243174,"remaining_time":1.821877446},
{"learn":[0.01684888463],"iteration":180,"passed_time":0.4013041126,"remaining_time":1.815845681},
{"learn":[0.01683716084],"iteration":181,"passed_time":0.402608584,"remaining_time":1.809526493},
{"learn":[0.01671872629],"iteration":182,"passed_time":0.4039863098,"remaining_time":1.803589154},
{"learn":[0.0165895489],"iteration":183,"passed_time":0.4053581473,"remaining_time":1.797675262},
{"learn":[0.01640001595],"iteration":184,"passed_time":0.4067416695,"remaining_time":1.791861949},
{"learn":[0.01623469587],"iteration":185,"passed_time":0.4080683196,"remaining_time":1.785847377},
{"learn":[0.01614396043],"iteration":186,"passed_time":0.4093787322,"remaining_time":1.779812349},
{"learn":[0.01610675415],"iteration":187,"passed_time":0.4106862092,"remaining_time":1.773814904},
{"learn":[0.01583313984],"iteration":188,"passed_time":0.4121096511,"remaining_time":1.768364693},
{"learn":[0.01573405178],"iteration":189,"passed_time":0.4134943048,"remaining_time":1.76279151},
{"learn":[0.0156875437],"iteration":190,"passed_time":0.414852066,"remaining_time":1.75714828},
{"learn":[0.01563010478],"iteration":191,"passed_time":0.4162115805,"remaining_time":1.751557068},
{"learn":[0.01544874385],"iteration":192,"passed_time":0.4176205575,"remaining_time":1.746216528},
{"learn":[0.01526443069],"iteration":193,"passed_time":0.4189855121,"remaining_time":1.740733623},
{"learn":[0.01505488346],"iteration":194,"passed_time":0.4203306597,"remaining_time":1.735211185},
{"learn":[0.01492586025],"iteration":195,"passed_time":0.4217358496,"remaining_time":1.729977669},
{"learn":[0.01480183055],"iteration":196,"passed_time":0.4231055459,"remaining_time":1.724638342},
{"learn":[0.01462951388],"iteration":197,"passed_time":0.4245135784,"remaining_time":1.719494393},
{"learn":[0.0145782039],"iteration":198,"passed_time":0.425885058,"remaining_time":1.714240862},
{"learn":[0.01453066691],"iteration":199,"passed_time":0.4273724618,"remaining_time":1.709489847},
{"learn":[0.01448970418],"iteration":200,"passed_time":0.4287204347,"remaining_time":1.704217051},
{"learn":[0.01433366173],"iteration":201,"passed_time":0.4301130511,"remaining_time":1.699159479},
{"learn":[0.0141693289],"iteration":202,"passed_time":0.4315492891,"remaining_time":1.694309278},
{"learn":[0.01405322794],"iteration":203,"passed_time":0.4329680845,"remaining_time":1.689424487},
{"learn":[0.01398294413],"iteration":204,"passed_time":0.4343744066,"remaining_time":1.684525138},
{"learn":[0.01388887803],"iteration":205,"passed_time":0.4357519948,"remaining_time":1.679548951},
{"learn":[0.01378547946],"iteration":206,"passed_time":0.4371412377,"remaining_time":1.674652181},
{"learn":[0.01367264438],"iteration":207,"passed_time":0.4385703825,"remaining_time":1.669941072},
{"learn":[0.0135210523],"iteration":208,"passed_time":0.4402107298,"remaining_time":1.666060705},
{"learn":[0.01343128642],"iteration":209,"passed_time":0.4417892068,"remaining_time":1.661968921},
{"learn":[0.01325299372],"iteration":210,"passed_time":0.4433345318,"remaining_time":1.657776993},
{"learn":[0.01321745373],"iteration":211,"passed_time":0.4447946818,"remaining_time":1.65329344},
{"learn":[0.01308711883],"iteration":212,"passed_time":0.4462034585,"remaining_time":1.648648459},
{"learn":[0.01295061875],"iteration":213,"passed_time":0.4476057129,"remaining_time":1.644009768},
{"learn":[0.01291098224],"iteration":214,"passed_time":0.4490250894,"remaining_time":1.639463698},
{"learn":[0.01281410182],"iteration":215,"passed_time":0.4503871486,"remaining_time":1.634738539},
{"learn":[0.01279970452],"iteration":216,"passed_time":0.4517682835,"remaining_time":1.630113207},
{"learn":[0.0126842779],"iteration":217,"passed_time":0.4531604892,"remaining_time":1.625557351},
{"learn":[0.01258037884],"iteration":218,"passed_time":0.454529822,"remaining_time":1.620948817},
{"learn":[0.01247496117],"iteration":219,"passed_time":0.4559385986,"remaining_time":1.616509577},
{"learn":[0.0123707986],"iteration":220,"passed_time":0.4573658126,"remaining_time":1.612162751},
{"learn":[0.01227321449],"iteration":221,"passed_time":0.4587547994,"remaining_time":1.607708261},
{"learn":[0.01216518178],"iteration":222,"passed_time":0.4601299631,"remaining_time":1.6032331},
{"learn":[0.01212958749],"iteration":223,"passed_time":0.4615122903,"remaining_time":1.598810434},
{"learn":[0.01203765247],"iteration":224,"passed_time":0.4629107677,"remaining_time":1.594470422},
{"learn":[0.01196461179],"iteration":225,"passed_time":0.4642672765,"remaining_time":1.590012708},
{"learn":[0.01186415629],"iteration":226,"passed_time":0.4656871138,"remaining_time":1.585797969},
{"learn":[0.01174459625],"iteration":227,"passed_time":0.467033103,"remaining_time":1.5813577},
{"learn":[0.01163967807],"iteration":228,"passed_time":0.4683976969,"remaining_time":1.577007093},
{"learn":[0.01158501411],"iteration":229,"passed_time":0.4697689433,"remaining_time":1.572704723},
{"learn":[0.01147871297],"iteration":230,"passed_time":0.4711268648,"remaining_time":1.568383372},
{"learn":[0.01139858878],"iteration":231,"passed_time":0.4724919597,"remaining_time":1.564111315},
{"learn":[0.0113228184],"iteration":232,"passed_time":0.473948208,"remaining_time":1.560164273},
{"learn":[0.01126107775],"iteration":233,"passed_time":0.4753004889,"remaining_time":1.555898182},
{"learn":[0.01112783835],"iteration":234,"passed_time":0.476689075,"remaining_time":1.551775074},
{"learn":[0.01106795601],"iteration":235,"passed_time":0.478104484,"remaining_time":1.547761974},
{"learn":[0.01097527393],"iteration":236,"passed_time":0.4795114701,"remaining_time":1.543743678},
{"learn":[0.01093509453],"iteration":237,"passed_time":0.4809158686,"remaining_time":1.539739041},
{"learn":[0.01079805992],"iteration":238,"passed_time":0.4823329279,"remaining_time":1.535796478},
{"learn":[0.01069445058],"iteration":239,"passed_time":0.4837559112,"remaining_time":1.531893719},
{"learn":[0.01058848239],"iteration":240,"passed_time":0.4851328482,"remaining_time":1.527866522},
{"learn":[0.01052363059],"iteration":241,"passed_time":0.4864627172,"remaining_time":1.5237138},
{"learn":[0.01046484242],"iteration":242,"passed_time":0.4878376906,"remaining_time":1.519724822},
{"learn":[0.01040922817],"iteration":243,"passed_time":0.4892494027,"remaining_time":1.5158711},
{"learn":[0.01037959649],"iteration":244,"passed_time":0.4906137935,"remaining_time":1.511891486},
{"learn":[0.0103555744],"iteration":245,"passed_time":0.4919865027,"remaining_time":1.50795863},
{"learn":[0.01028799461],"iteration":246,"passed_time":0.4933439432,"remaining_time":1.503999957},
{"learn":[0.01021160202],"iteration":247,"passed_time":0.4947446949,"remaining_time":1.500193591},
{"learn":[0.01014731816],"iteration":248,"passed_time":0.496128084,"remaining_time":1.496354181},
{"learn":[0.01004371617],"iteration":249,"passed_time":0.497512996,"remaining_time":1.492538988},
{"learn":[0.009924095127],"iteration":250,"passed_time":0.4988825492,"remaining_time":1.488697328},
{"learn":[0.009792910545],"iteration":251,"passed_time":0.5003391754,"remaining_time":1.485133743},
{"learn":[0.009701821034],"iteration":252,"passed_time":0.5017022593,"remaining_time":1.481310623},
{"learn":[0.009658406089],"iteration":253,"passed_time":0.5030830108,"remaining_time":1.477558764},
{"learn":[0.009613030081],"iteration":254,"passed_time":0.5045597045,"remaining_time":1.474105803},
{"learn":[0.009517817709],"iteration":255,"passed_time":0.5059520705,"remaining_time":1.470423205},
{"learn":[0.009476159176],"iteration":256,"passed_time":0.5073199606,"remaining_time":1.466687668},
{"learn":[0.009376673757],"iteration":257,"passed_time":0.5086929503,"remaining_time":1.462985152},
{"learn":[0.009311976498],"iteration":258,"passed_time":0.5100506213,"remaining_time":1.459256797},
{"learn":[0.009247827013],"iteration":259,"passed_time":0.5114348119,"remaining_time":1.455622157},
{"learn":[0.009165176226],"iteration":260,"passed_time":0.5128341709,"remaining_time":1.45204771},
{"learn":[0.009115968654],"iteration":261,"passed_time":0.5142535875,"remaining_time":1.448546365},
{"learn":[0.009012433043],"iteration":262,"passed_time":0.5156582164,"remaining_time":1.445019412},
{"learn":[0.008919289222],"iteration":263,"passed_time":0.5170537082,"remaining_time":1.441483065},
{"learn":[0.00890232095],"iteration":264,"passed_time":0.5184665652,"remaining_time":1.438011039},
{"learn":[0.008841432024],"iteration":265,"passed_time":0.5199686237,"remaining_time":1.434800638},
{"learn":[0.008827745519],"iteration":266,"passed_time":0.521321248,"remaining_time":1.431192789},
{"learn":[0.008790914672],"iteration":267,"passed_time":0.5227022098,"remaining_time":1.42767917},
{"learn":[0.008755677559],"iteration":268,"passed_time":0.5240804293,"remaining_time":1.424173955},
{"learn":[0.008736982651],"iteration":269,"passed_time":0.5254153677,"remaining_time":1.420567476},
{"learn":[0.008661002299],"iteration":270,"passed_time":0.5268492113,"remaining_time":1.417243819},
{"learn":[0.008618334056],"iteration":271,"passed_time":0.5281924453,"remaining_time":1.413691545},
{"learn":[0.008559177035],"iteration":272,"passed_time":0.5295606159,"remaining_time":1.41022186},
{"learn":[0.008516783801],"iteration":273,"passed_time":0.5309272938,"remaining_time":1.406763559},
{"learn":[0.008423196136],"iteration":274,"passed_time":0.5323516997,"remaining_time":1.403472663},
{"learn":[0.00836326949],"iteration":275,"passed_time":0.5337076775,"remaining_time":1.400015792},
{"learn":[0.008341480844],"iteration":276,"passed_time":0.5351600658,"remaining_time":1.396825731},
{"learn":[0.008304391323],"iteration":277,"passed_time":0.5365468613,"remaining_time":1.39347782},
{"learn":[0.008248581471],"iteration":278,"passed_time":0.537928397,"remaining_time":1.390130374},
{"learn":[0.008233023241],"iteration":279,"passed_time":0.5393140003,"remaining_time":1.386807429},
{"learn":[0.008194601599],"iteration":280,"passed_time":0.540659228,"remaining_time":1.383394964},
{"learn":[0.008135097281],"iteration":281,"passed_time":0.5420268704,"remaining_time":1.38005423},
{"learn":[0.008097377015],"iteration":282,"passed_time":0.5433987352,"remaining_time":1.376738138},
{"learn":[0.008025946078],"iteration":283,"passed_time":0.5448366564,"remaining_time":1.373602275},
{"learn":[0.007990795999],"iteration":284,"passed_time":0.5462254857,"remaining_time":1.370355166},
{"learn":[0.007974195737],"iteration":285,"passed_time":0.5476803586,"remaining_time":1.36728593},
{"learn":[0.007928434041],"iteration":286,"passed_time":0.5490587785,"remaining_time":1.364038011},
{"learn":[0.007900862383],"iteration":287,"passed_time":0.550549779,"remaining_time":1.361081398},
{"learn":[0.007858308142],"iteration":288,"passed_time":0.5519483666,"remaining_time":1.357907573},
{"learn":[0.007768958806],"iteration":289,"passed_time":0.5533033225,"remaining_time":1.354639169},
{"learn":[0.007728735262],"iteration":290,"passed_time":0.5546595608,"remaining_time":1.35138704},
{"learn":[0.007641848357],"iteration":291,"passed_time":0.556057377,"remaining_time":1.348248709},
{"learn":[0.007602022849],"iteration":292,"passed_time":0.5573866248,"remaining_time":1.344956804},
{"learn":[0.007567589792],"iteration":293,"passed_time":0.5587370221,"remaining_time":1.34172904},
{"learn":[0.007515718918],"iteration":294,"passed_time":0.5601377738,"remaining_time":1.338634341},
{"learn":[0.007472398082],"iteration":295,"passed_time":0.5615168649,"remaining_time":1.33549957},
{"learn":[0.007440329071],"iteration":296,"passed_time":0.5629001638,"remaining_time":1.332386583},
{"learn":[0.00741505079],"iteration":297,"passed_time":0.5642541479,"remaining_time":1.329216147},
{"learn":[0.007392509518],"iteration":298,"passed_time":0.5657573942,"remaining_time":1.326407804},
{"learn":[0.007359560545],"iteration":299,"passed_time":0.5671627845,"remaining_time":1.32337983},
{"learn":[0.007305381069],"iteration":300,"passed_time":0.5685236587,"remaining_time":1.320259261},
{"learn":[0.007240642449],"iteration":301,"passed_time":0.5698981512,"remaining_time":1.31718182},
{"learn":[0.007178855798],"iteration":302,"passed_time":0.5712639975,"remaining_time":1.31409573},
{"learn":[0.007158537758],"iteration":303,"passed_time":0.5726563935,"remaining_time":1.311081743},
{"learn":[0.007102156659],"iteration":304,"passed_time":0.5740280306,"remaining_time":1.308031086},
{"learn":[0.00704919555],"iteration":305,"passed_time":0.5754119635,"remaining_time":1.30501929},
{"learn":[0.007011384993],"iteration":306,"passed_time":0.5768178119,"remaining_time":1.302067569},
{"learn":[0.006976732905],"iteration":307,"passed_time":0.5782074528,"remaining_time":1.299089472},
{"learn":[0.006928549351],"iteration":308,"passed_time":0.5795584112,"remaining_time":1.296035153},
{"learn":[0.006907747159],"iteration":309,"passed_time":0.5809628698,"remaining_time":1.293110904},
{"learn":[0.006886390334],"iteration":310,"passed_time":0.5823069882,"remaining_time":1.290062749},
{"learn":[0.006870222351],"iteration":311,"passed_time":0.5836988404,"remaining_time":1.287130776},
{"learn":[0.006845915241],"iteration":312,"passed_time":0.5850193719,"remaining_time":1.284052104},
{"learn":[0.006816662742],"iteration":313,"passed_time":0.586380973,"remaining_time":1.281074355},
{"learn":[0.006765941302],"iteration":314,"passed_time":0.5877939347,"remaining_time":1.278218556},
{"learn":[0.006750469838],"iteration":315,"passed_time":0.5891171412,"remaining_time":1.275177609},
{"learn":[0.006710259837],"iteration":316,"passed_time":0.5904753532,"remaining_time":1.272222922},
{"learn":[0.006667914386],"iteration":317,"passed_time":0.5918933972,"remaining_time":1.269406594},
{"learn":[0.006615781964],"iteration":318,"passed_time":0.5932706677,"remaining_time":1.26651199},
{"learn":[0.006566354549],"iteration":319,"passed_time":0.5946918247,"remaining_time":1.263720128},
{"learn":[0.006549566783],"iteration":320,"passed_time":0.5960498865,"remaining_time":1.260803342},
{"learn":[0.006505156141],"iteration":321,"passed_time":0.5974487946,"remaining_time":1.257982245},
{"learn":[0.006477458848],"iteration":322,"passed_time":0.5988585258,"remaining_time":1.255192638},
{"learn":[0.006448377975],"iteration":323,"passed_time":0.6002563793,"remaining_time":1.252386767},
{"learn":[0.006396832218],"iteration":324,"passed_time":0.6016541253,"remaining_time":1.249589337},
{"learn":[0.006367775528],"iteration":325,"passed_time":0.6030349496,"remaining_time":1.246765509},
{"learn":[0.006348367852],"iteration":326,"passed_time":0.604391769,"remaining_time":1.243901103},
{"learn":[0.006332867602],"iteration":327,"passed_time":0.6057518044,"remaining_time":1.241052477},
{"learn":[0.006293483886],"iteration":328,"passed_time":0.6071835769,"remaining_time":1.23835921},
{"learn":[0.006248287764],"iteration":329,"passed_time":0.608596218,"remaining_time":1.235634746},
{"learn":[0.006200025334],"iteration":330,"passed_time":0.6100092927,"remaining_time":1.232919084},
{"learn":[0.006182921723],"iteration":331,"passed_time":0.611444181,"remaining_time":1.230255159},
{"learn":[0.006182914468],"iteration":332,"passed_time":0.6127638281,"remaining_time":1.227367788},
{"learn":[0.006159160233],"iteration":333,"passed_time":0.6142490005,"remaining_time":1.224819863},
{"learn":[0.006128891039],"iteration":334,"passed_time":0.615695545,"remaining_time":1.222201604},
{"learn":[0.00610294263],"iteration":335,"passed_time":0.6170598112,"remaining_time":1.219427722},
{"learn":[0.006083687862],"iteration":336,"passed_time":0.6184210861,"remaining_time":1.216656321},
{"learn":[0.006040549117],"iteration":337,"passed_time":0.6198405127,"remaining_time":1.214007158},
{"learn":[0.006002764937],"iteration":338,"passed_time":0.6212098956,"remaining_time":1.211267673},
{"learn":[0.005978108868],"iteration":339,"passed_time":0.6225735606,"remaining_time":1.208525147},
{"learn":[0.005965719883],"iteration":340,"passed_time":0.6239325213,"remaining_time":1.205781617},
{"learn":[0.005933979593],"iteration":341,"passed_time":0.6253235948,"remaining_time":1.203107969},
{"learn":[0.005909290864],"iteration":342,"passed_time":0.6267396328,"remaining_time":1.200489617},
{"learn":[0.005872492407],"iteration":343,"passed_time":0.6282691003,"remaining_time":1.198094563},
{"learn":[0.005829870593],"iteration":344,"passed_time":0.6296104708,"remaining_time":1.195347416},
{"learn":[0.005797904406],"iteration":345,"passed_time":0.6309577095,"remaining_time":1.192619486},
{"learn":[0.005756029871],"iteration":346,"passed_time":0.6323138677,"remaining_time":1.189916299},
{"learn":[0.005742863494],"iteration":347,"passed_time":0.6336939707,"remaining_time":1.187265715},
{"learn":[0.005717541976],"iteration":348,"passed_time":0.6351030479,"remaining_time":1.184676459},
{"learn":[0.005699031079],"iteration":349,"passed_time":0.6364798246,"remaining_time":1.18203396},
{"learn":[0.005671273584],"iteration":350,"passed_time":0.6378830108,"remaining_time":1.179447504},
{"learn":[0.005654013949],"iteration":351,"passed_time":0.6392459144,"remaining_time":1.176793615},
{"learn":[0.005630197402],"iteration":352,"passed_time":0.6405882166,"remaining_time":1.174109281},
{"learn":[0.005592911236],"iteration":353,"passed_time":0.6419903759,"remaining_time":1.171541759},
{"learn":[0.005564132213],"iteration":354,"passed_time":0.6433358563,"remaining_time":1.168877823},
{"learn":[0.005533089037],"iteration":355,"passed_time":0.6446937377,"remaining_time":1.166243728},
{"learn":[0.005512998181],"iteration":356,"passed_time":0.646072929,"remaining_time":1.163655163},
{"learn":[0.005492299956],"iteration":357,"passed_time":0.6474569693,"remaining_time":1.161082051},
{"learn":[0.005480105581],"iteration":358,"passed_time":0.6488331578,"remaining_time":1.158501544},
{"learn":[0.005459072783],"iteration":359,"passed_time":0.6501797853,"remaining_time":1.155875174},
{"learn":[0.00543587446],"iteration":360,"passed_time":0.6515160863,"remaining_time":1.153237615},
{"learn":[0.005410220703],"iteration":361,"passed_time":0.6529247728,"remaining_time":1.150734821},
{"learn":[0.005370067384],"iteration":362,"passed_time":0.6543325376,"remaining_time":1.148236436},
{"learn":[0.005347095291],"iteration":363,"passed_time":0.6556698833,"remaining_time":1.145621005},
{"learn":[0.005327408595],"iteration":364,"passed_time":0.657044924,"remaining_time":1.143078156},
{"learn":[0.005315442931],"iteration":365,"passed_time":0.6584717645,"remaining_time":1.140631417},
{"learn":[0.005315404278],"iteration":366,"passed_time":0.6596716001,"remaining_time":1.1377987},
{"learn":[0.005315426469],"iteration":367,"passed_time":0.6608856395,"remaining_time":1.13499925},
{"learn":[0.005294852513],"iteration":368,"passed_time":0.6622524003,"remaining_time":1.132469552},
{"learn":[0.005273713228],"iteration":369,"passed_time":0.6636099711,"remaining_time":1.129930491},
{"learn":[0.005263726554],"iteration":370,"passed_time":0.6649768465,"remaining_time":1.127413575},
{"learn":[0.00525286606],"iteration":371,"passed_time":0.6663373629,"remaining_time":1.124892107},
{"learn":[0.005245499367],"iteration":372,"passed_time":0.6676758179,"remaining_time":1.12233978},
{"learn":[0.005211554402],"iteration":373,"passed_time":0.6690351648,"remaining_time":1.119828912},
{"learn":[0.005185909959],"iteration":374,"passed_time":0.6704217171,"remaining_time":1.117369528},
{"learn":[0.005165511604],"iteration":375,"passed_time":0.6717896473,"remaining_time":1.114884947},
{"learn":[0.005156400835],"iteration":376,"passed_time":0.6732571438,"remaining_time":1.112570824},
{"learn":[0.005135192874],"iteration":377,"passed_time":0.6746411942,"remaining_time":1.11012387},
{"learn":[0.005107990125],"iteration":378,"passed_time":0.6760026423,"remaining_time":1.10764549},
{"learn":[0.005095722035],"iteration":379,"passed_time":0.6772895308,"remaining_time":1.10505134},
{"learn":[0.005081086779],"iteration":380,"passed_time":0.6786735311,"remaining_time":1.102621826},
{"learn":[0.005059208847],"iteration":381,"passed_time":0.6800366723,"remaining_time":1.100164041},
{"learn":[0.005038668859],"iteration":382,"passed_time":0.6814023283,"remaining_time":1.097716022},
{"learn":[0.005028566673],"iteration":383,"passed_time":0.68272686,"remaining_time":1.095207671},
{"learn":[0.004996062398],"iteration":384,"passed_time":0.6841056177,"remaining_time":1.092792091},
{"learn":[0.004952027586],"iteration":385,"passed_time":0.6854854001,"remaining_time":1.090383512},
{"learn":[0.004933553804],"iteration":386,"passed_time":0.6868179641,"remaining_time":1.087905457},
{"learn":[0.004920644832],"iteration":387,"passed_time":0.6882263328,"remaining_time":1.085552875},
{"learn":[0.004908806113],"iteration":388,"passed_time":0.6896622575,"remaining_time":1.08324843},
{"learn":[0.004890508205],"iteration":389,"passed_time":0.6910682589,"remaining_time":1.080901636},
{"learn":[0.004872162436],"iteration":390,"passed_time":0.6924537019,"remaining_time":1.078527633},
{"learn":[0.004854301239],"iteration":391,"passed_time":0.6938679187,"remaining_time":1.076203303},
{"learn":[0.004835442268],"iteration":392,"passed_time":0.6952529008,"remaining_time":1.07383845},
{"learn":[0.0048102665],"iteration":393,"passed_time":0.6966171569,"remaining_time":1.071446693},
{"learn":[0.004781398546],"iteration":394,"passed_time":0.6979925584,"remaining_time":1.06907721},
{"learn":[0.004767708266],"iteration":395,"passed_time":0.6993932527,"remaining_time":1.066751325},
{"learn":[0.004751184689],"iteration":396,"passed_time":0.700780356,"remaining_time":1.064409458},
{"learn":[0.004751099189],"iteration":397,"passed_time":0.7020324694,"remaining_time":1.061868207},
{"learn":[0.004736351926],"iteration":398,"passed_time":0.7034615418,"remaining_time":1.059599966},
{"learn":[0.004716464389],"iteration":399,"passed_time":0.7048393828,"remaining_time":1.057259074},
{"learn":[0.004701934071],"iteration":400,"passed_time":0.7062007908,"remaining_time":1.054898438},
{"learn":[0.004674269565],"iteration":401,"passed_time":0.7075767761,"remaining_time":1.052564458},
{"learn":[0.004648894578],"iteration":402,"passed_time":0.7089514689,"remaining_time":1.050233317},
{"learn":[0.004635301589],"iteration":403,"passed_time":0.7103177688,"remaining_time":1.04789453},
{"learn":[0.004622718195],"iteration":404,"passed_time":0.7116776813,"remaining_time":1.045551161},
{"learn":[0.004607485774],"iteration":405,"passed_time":0.7130659796,"remaining_time":1.043254167},
{"learn":[0.004589410399],"iteration":406,"passed_time":0.7144449605,"remaining_time":1.040948063},
{"learn":[0.004573250492],"iteration":407,"passed_time":0.7158065115,"remaining_time":1.038621213},
{"learn":[0.004542170268],"iteration":408,"passed_time":0.7171773343,"remaining_time":1.036312481},
{"learn":[0.004534218561],"iteration":409,"passed_time":0.7185994359,"remaining_time":1.034082115},
{"learn":[0.004525529351],"iteration":410,"passed_time":0.7199676595,"remaining_time":1.031778471},
{"learn":[0.004506110075],"iteration":411,"passed_time":0.7213302469,"remaining_time":1.029471323},
{"learn":[0.004482782953],"iteration":412,"passed_time":0.7227095584,"remaining_time":1.02719252},
{"learn":[0.004482686443],"iteration":413,"passed_time":0.7239730131,"remaining_time":1.024754072},
{"learn":[0.004480207667],"iteration":414,"passed_time":0.7252116413,"remaining_time":1.022286289},
{"learn":[0.004473323982],"iteration":415,"passed_time":0.7265647036,"remaining_time":1.019985065},
{"learn":[0.004452671436],"iteration":416,"passed_time":0.727992669,"remaining_time":1.017793108},
{"learn":[0.004441796173],"iteration":417,"passed_time":0.7293882782,"remaining_time":1.015559756},
{"learn":[0.004434513456],"iteration":418,"passed_time":0.7307258616,"remaining_time":1.013249942},
{"learn":[0.004422594433],"iteration":419,"passed_time":0.7320780323,"remaining_time":1.010964902},
{"learn":[0.004412745052],"iteration":420,"passed_time":0.7336094463,"remaining_time":1.008930806},
{"learn":[0.004397902586],"iteration":421,"passed_time":0.7352631808,"remaining_time":1.007066632},
{"learn":[0.004397898606],"iteration":422,"passed_time":0.7367295781,"remaining_time":1.004947911},
{"learn":[0.004391256412],"iteration":423,"passed_time":0.73817176,"remaining_time":1.002799372},
{"learn":[0.004378931724],"iteration":424,"passed_time":0.7397626475,"remaining_time":1.000855347},
{"learn":[0.004363856327],"iteration":425,"passed_time":0.7412194813,"remaining_time":0.9987323528},
{"learn":[0.004358489364],"iteration":426,"passed_time":0.7425579865,"remaining_time":0.9964536914},
{"learn":[0.004347623199],"iteration":427,"passed_time":0.7438674673,"remaining_time":0.9941406338},
{"learn":[0.004328903819],"iteration":428,"passed_time":0.7452530605,"remaining_time":0.9919335608},
{"learn":[0.00432880631],"iteration":429,"passed_time":0.7464623639,"remaining_time":0.9894966219},
{"learn":[0.004309913576],"iteration":430,"passed_time":0.7478553287,"remaining_time":0.9873078469},
{"learn":[0.00430994187],"iteration":431,"passed_time":0.7490716173,"remaining_time":0.9848904598},
{"learn":[0.004293824729],"iteration":432,"passed_time":0.7504059446,"remaining_time":0.9826331884},
{"learn":[0.004293817133],"iteration":433,"passed_time":0.7515738404,"remaining_time":0.9801631191},
{"learn":[0.004286714448],"iteration":434,"passed_time":0.7529466898,"remaining_time":0.9779652408},
{"learn":[0.004286447389],"iteration":435,"passed_time":0.7541597903,"remaining_time":0.9755644993},
{"learn":[0.004286445266],"iteration":436,"passed_time":0.755314404,"remaining_time":0.9730938431},
{"learn":[0.004276937574],"iteration":437,"passed_time":0.7567668724,"remaining_time":0.9710113751},
{"learn":[0.004264022791],"iteration":438,"passed_time":0.7583003825,"remaining_time":0.9690353408},
{"learn":[0.004248433255],"iteration":439,"passed_time":0.759672628,"remaining_time":0.966856072},
{"learn":[0.004234165396],"iteration":440,"passed_time":0.7610498456,"remaining_time":0.9646867658},
{"learn":[0.004224017605],"iteration":441,"passed_time":0.7623838924,"remaining_time":0.9624665429},
{"learn":[0.00420538035],"iteration":442,"passed_time":0.7638727088,"remaining_time":0.9604449183},
{"learn":[0.004190751887],"iteration":443,"passed_time":0.7652282787,"remaining_time":0.9582588355},
{"learn":[0.004174762794],"iteration":444,"passed_time":0.766635169,"remaining_time":0.9561404917},
{"learn":[0.004165621555],"iteration":445,"passed_time":0.7679589466,"remaining_time":0.9539220996},
{"learn":[0.004158593849],"iteration":446,"passed_time":0.7693215568,"remaining_time":0.9517557515},
{"learn":[0.004143826252],"iteration":447,"passed_time":0.7706925355,"remaining_time":0.9496033027},
{"learn":[0.00413300306],"iteration":448,"passed_time":0.7720643803,"remaining_time":0.9474553976},
{"learn":[0.004127425979],"iteration":449,"passed_time":0.7733790408,"remaining_time":0.9452410498},
{"learn":[0.004114193616],"iteration":450,"passed_time":0.7747277951,"remaining_time":0.943072194},
{"learn":[0.00409175143],"iteration":451,"passed_time":0.7760904154,"remaining_time":0.9409237779},
{"learn":[0.004089554537],"iteration":452,"passed_time":0.7773493816,"remaining_time":0.9386536683},
{"learn":[0.004089515424],"iteration":453,"passed_time":0.7786722775,"remaining_time":0.9364648977},
{"learn":[0.004069124448],"iteration":454,"passed_time":0.7800721074,"remaining_time":0.9343720847},
{"learn":[0.004065429542],"iteration":455,"passed_time":0.781338177,"remaining_time":0.9321227375},
{"learn":[0.004042726969],"iteration":456,"passed_time":0.7827030315,"remaining_time":0.929995068},
{"learn":[0.004022130772],"iteration":457,"passed_time":0.7840634404,"remaining_time":0.9278654687},
{"learn":[0.004005439464],"iteration":458,"passed_time":0.7854632074,"remaining_time":0.9257856104},
{"learn":[0.003988777988],"iteration":459,"passed_time":0.7868673353,"remaining_time":0.9237138284},
{"learn":[0.003975097924],"iteration":460,"passed_time":0.7882653418,"remaining_time":0.9216377858},
{"learn":[0.003962659333],"iteration":461,"passed_time":0.7896230028,"remaining_time":0.9195176959},
{"learn":[0.003953858281],"iteration":462,"passed_time":0.791025781,"remaining_time":0.9174532276},
{"learn":[0.003948987814],"iteration":463,"passed_time":0.7923886189,"remaining_time":0.9153454735},
{"learn":[0.003946427275],"iteration":464,"passed_time":0.7936958032,"remaining_time":0.9131768918},
{"learn":[0.003946414612],"iteration":465,"passed_time":0.7949074008,"remaining_time":0.9109024721},
{"learn":[0.00392269487],"iteration":466,"passed_time":0.7963100482,"remaining_time":0.9088506546},
{"learn":[0.003901954519],"iteration":467,"passed_time":0.7976969166,"remaining_time":0.9067836744},
{"learn":[0.003887979403],"iteration":468,"passed_time":0.7990330846,"remaining_time":0.9046621917},
{"learn":[0.00388309562],"iteration":469,"passed_time":0.8003688346,"remaining_time":0.9025435794},
{"learn":[0.003867899604],"iteration":470,"passed_time":0.8017310068,"remaining_time":0.9004579673},
{"learn":[0.003858443918],"iteration":471,"passed_time":0.8030952773,"remaining_time":0.8983777679},
{"learn":[0.003836083136],"iteration":472,"passed_time":0.8044696496,"remaining_time":0.8963118506},
{"learn":[0.003822904219],"iteration":473,"passed_time":0.8058032956,"remaining_time":0.8942036572},
{"learn":[0.003813956614],"iteration":474,"passed_time":0.8071770367,"remaining_time":0.8921430406},
{"learn":[0.00380229138],"iteration":475,"passed_time":0.8085281755,"remaining_time":0.8900604285},
{"learn":[0.003788868753],"iteration":476,"passed_time":0.8100409468,"remaining_time":0.8881581031},
{"learn":[0.003773177322],"iteration":477,"passed_time":0.8114128945,"remaining_time":0.8861036212},
{"learn":[0.003765424259],"iteration":478,"passed_time":0.8127524917,"remaining_time":0.884016802},
{"learn":[0.003765407893],"iteration":479,"passed_time":0.8139539904,"remaining_time":0.8817834896},
{"learn":[0.003762229347],"iteration":480,"passed_time":0.8152990177,"remaining_time":0.8797093351},
{"learn":[0.003759119189],"iteration":481,"passed_time":0.8166174653,"remaining_time":0.8776096411},
{"learn":[0.003759116041],"iteration":482,"passed_time":0.8179317952,"remaining_time":0.8755087746},
{"learn":[0.00375912862],"iteration":483,"passed_time":0.8192398333,"remaining_time":0.8734044504},
{"learn":[0.003748201171],"iteration":484,"passed_time":0.8208109065,"remaining_time":0.8715827151},
{"learn":[0.003733689009],"iteration":485,"passed_time":0.8222298894,"remaining_time":0.8696011588},
{"learn":[0.003715423957],"iteration":486,"passed_time":0.8236248731,"remaining_time":0.8675966322},
{"learn":[0.003703825726],"iteration":487,"passed_time":0.8250352627,"remaining_time":0.8656107674},
{"learn":[0.003692220949],"iteration":488,"passed_time":0.8264025189,"remaining_time":0.8635821823},
{"learn":[0.003680573673],"iteration":489,"passed_time":0.8277722424,"remaining_time":0.8615588646},
{"learn":[0.003669307139],"iteration":490,"passed_time":0.8291497105,"remaining_time":0.8595462376},
{"learn":[0.003658998935],"iteration":491,"passed_time":0.8304788008,"remaining_time":0.8574862415},
{"learn":[0.003648209836],"iteration":492,"passed_time":0.8318464505,"remaining_time":0.8554688649},
{"learn":[0.003643277766],"iteration":493,"passed_time":0.8332285171,"remaining_time":0.853468886},
{"learn":[0.00364089212],"iteration":494,"passed_time":0.8345604672,"remaining_time":0.8514202746},
{"learn":[0.003637562532],"iteration":495,"passed_time":0.8359076285,"remaining_time":0.8493900096},
{"learn":[0.003630101238],"iteration":496,"passed_time":0.8372909676,"remaining_time":0.847399108},
{"learn":[0.003619110283],"iteration":497,"passed_time":0.8386817806,"remaining_time":0.8454181804},
{"learn":[0.003606817354],"iteration":498,"passed_time":0.8401412193,"remaining_time":0.8435085188},
{"learn":[0.003586857002],"iteration":499,"passed_time":0.8415501791,"remaining_time":0.8415501791},
{"learn":[0.003577835937],"iteration":500,"passed_time":0.8429312839,"remaining_time":0.8395662888},
{"learn":[0.003561682719],"iteration":501,"passed_time":0.8442907182,"remaining_time":0.8375633021},
{"learn":[0.003552848978],"iteration":502,"passed_time":0.845665882,"remaining_time":0.8355784162},
{"learn":[0.003542483547],"iteration":503,"passed_time":0.8471726748,"remaining_time":0.8337254895},
{"learn":[0.003534071842],"iteration":504,"passed_time":0.8485620925,"remaining_time":0.8317588827},
{"learn":[0.003532173894],"iteration":505,"passed_time":0.8497900207,"remaining_time":0.8296368976},
{"learn":[0.003515486156],"iteration":506,"passed_time":0.8511654349,"remaining_time":0.8276618528},
{"learn":[0.00350696843],"iteration":507,"passed_time":0.8525267226,"remaining_time":0.8256754873},
{"learn":[0.003493437323],"iteration":508,"passed_time":0.8538709885,"remaining_time":0.8236751579},
{"learn":[0.003482469029],"iteration":509,"passed_time":0.8552818992,"remaining_time":0.8217414326},
{"learn":[0.003469862787],"iteration":510,"passed_time":0.856622899,"remaining_time":0.8197428525},
{"learn":[0.003467657678],"iteration":511,"passed_time":0.8578625691,"remaining_time":0.8176502612},
{"learn":[0.003457309372],"iteration":512,"passed_time":0.8592499786,"remaining_time":0.8157012467},
{"learn":[0.003442478635],"iteration":513,"passed_time":0.8606427625,"remaining_time":0.8137594992},
{"learn":[0.003431073959],"iteration":514,"passed_time":0.8620201404,"remaining_time":0.8118053749},
{"learn":[0.003423915225],"iteration":515,"passed_time":0.8633694758,"remaining_time":0.8098271827},
{"learn":[0.003416258427],"iteration":516,"passed_time":0.8648718805,"remaining_time":0.807994426},
{"learn":[0.00341627027],"iteration":517,"passed_time":0.8662767771,"remaining_time":0.8060722134},
{"learn":[0.00341616972],"iteration":518,"passed_time":0.8675287502,"remaining_time":0.8040102676},
{"learn":[0.003416164449],"iteration":519,"passed_time":0.8687422113,"remaining_time":0.8019158874},
{"learn":[0.003408944737],"iteration":520,"passed_time":0.8701097007,"remaining_time":0.7999665003},
{"learn":[0.003397380231],"iteration":521,"passed_time":0.8715851421,"remaining_time":0.7981181953},
{"learn":[0.003390608756],"iteration":522,"passed_time":0.8729518,"remaining_time":0.7961721005},
{"learn":[0.003390613472],"iteration":523,"passed_time":0.8741621252,"remaining_time":0.7940862053},
{"learn":[0.003390574093],"iteration":524,"passed_time":0.8753974973,"remaining_time":0.7920263071},
{"learn":[0.003379592516],"iteration":525,"passed_time":0.8767920974,"remaining_time":0.7901130307},
{"learn":[0.003371678676],"iteration":526,"passed_time":0.8782170944,"remaining_time":0.788229005},
{"learn":[0.00336395936],"iteration":527,"passed_time":0.8795810472,"remaining_time":0.7862921482},
{"learn":[0.0033559456],"iteration":528,"passed_time":0.8809458315,"remaining_time":0.7843581978},
{"learn":[0.003355955587],"iteration":529,"passed_time":0.8821582907,"remaining_time":0.7822913144},
{"learn":[0.003355910927],"iteration":530,"passed_time":0.8833279098,"remaining_time":0.7801898111},
{"learn":[0.003355848502],"iteration":531,"passed_time":0.8845187185,"remaining_time":0.7781104516},
{"learn":[0.003355610014],"iteration":532,"passed_time":0.8857815119,"remaining_time":0.7760974973},
{"learn":[0.003355641733],"iteration":533,"passed_time":0.8869386776,"remaining_time":0.7739951756},
{"learn":[0.003355538543],"iteration":534,"passed_time":0.8881640811,"remaining_time":0.7719556966},
{"learn":[0.003355497862],"iteration":535,"passed_time":0.8893454922,"remaining_time":0.7698811723},
{"learn":[0.003355462186],"iteration":536,"passed_time":0.8905392464,"remaining_time":0.7678206166},
{"learn":[0.003342458234],"iteration":537,"passed_time":0.8919217467,"remaining_time":0.7659253661},
{"learn":[0.003342458234],"iteration":538,"passed_time":0.8931278312,"remaining_time":0.763881132},
{"learn":[0.00334157142],"iteration":539,"passed_time":0.8943962752,"remaining_time":0.7618931233},
{"learn":[0.003341576135],"iteration":540,"passed_time":0.8955605342,"remaining_time":0.7598193811},
{"learn":[0.003328684628],"iteration":541,"passed_time":0.8969109015,"remaining_time":0.75790626},
{"learn":[0.003328664101],"iteration":542,"passed_time":0.8981103965,"remaining_time":0.7558682342},
{"learn":[0.003328656611],"iteration":543,"passed_time":0.8992920007,"remaining_time":0.7538182947},
{"learn":[0.00332865994],"iteration":544,"passed_time":0.9005222204,"remaining_time":0.751812129},
{"learn":[0.00332861792],"iteration":545,"passed_time":0.9017960645,"remaining_time":0.7498450793},
{"learn":[0.003328603773],"iteration":546,"passed_time":0.9030177811,"remaining_time":0.7478373946},
{"learn":[0.003328598598],"iteration":547,"passed_time":0.9042265434,"remaining_time":0.7458218935},
{"learn":[0.003328577143],"iteration":548,"passed_time":0.9054220108,"remaining_time":0.7437984096},
{"learn":[0.003328549415],"iteration":549,"passed_time":0.9066476046,"remaining_time":0.7418025856},
{"learn":[0.003315844539],"iteration":550,"passed_time":0.9080209349,"remaining_time":0.7399299452},
{"learn":[0.003296226238],"iteration":551,"passed_time":0.9093651207,"remaining_time":0.7380354603},
{"learn":[0.003281642632],"iteration":552,"passed_time":0.9107527377,"remaining_time":0.7361780719},
{"learn":[0.003273111414],"iteration":553,"passed_time":0.9121159591,"remaining_time":0.7343027397},
{"learn":[0.003264953039],"iteration":554,"passed_time":0.9135278716,"remaining_time":0.7324682935},
{"learn":[0.003264941943],"iteration":555,"passed_time":0.9147273866,"remaining_time":0.7304657548},
{"learn":[0.003264949155],"iteration":556,"passed_time":0.9159319138,"remaining_time":0.7284700858},
{"learn":[0.003258285288],"iteration":557,"passed_time":0.9174307162,"remaining_time":0.7267103522},
{"learn":[0.003258176129],"iteration":558,"passed_time":0.9186210239,"remaining_time":0.7247081781},
{"learn":[0.00325302557],"iteration":559,"passed_time":0.9199606011,"remaining_time":0.7228261866},
{"learn":[0.003252992006],"iteration":560,"passed_time":0.9211517103,"remaining_time":0.720829948},
{"learn":[0.003247002677],"iteration":561,"passed_time":0.9225120792,"remaining_time":0.7189684887},
{"learn":[0.003247017379],"iteration":562,"passed_time":0.9237440421,"remaining_time":0.717009141},
{"learn":[0.003246924549],"iteration":563,"passed_time":0.9249796146,"remaining_time":0.7150551631},
{"learn":[0.003246918012],"iteration":564,"passed_time":0.9261823083,"remaining_time":0.7130784144},
{"learn":[0.003246916625],"iteration":565,"passed_time":0.9274143314,"remaining_time":0.7111268901},
{"learn":[0.003246854319],"iteration":566,"passed_time":0.9285836298,"remaining_time":0.709130003},
{"learn":[0.003241156481],"iteration":567,"passed_time":0.9298910746,"remaining_time":0.707241099},
{"learn":[0.003238437137],"iteration":568,"passed_time":0.9312654491,"remaining_time":0.7054049359},
{"learn":[0.003235570677],"iteration":569,"passed_time":0.9328869567,"remaining_time":0.7037568269},
{"learn":[0.003235543311],"iteration":570,"passed_time":0.9342645622,"remaining_time":0.7019255642},
{"learn":[0.003233304683],"iteration":571,"passed_time":0.9354982211,"remaining_time":0.6999881794},
{"learn":[0.003233220996],"iteration":572,"passed_time":0.9367564988,"remaining_time":0.6980715969},
{"learn":[0.003224958544],"iteration":573,"passed_time":0.9381097187,"remaining_time":0.6962277704},
{"learn":[0.003206166473],"iteration":574,"passed_time":0.9394671192,"remaining_time":0.6943887403},
{"learn":[0.003206155377],"iteration":575,"passed_time":0.9407229196,"remaining_time":0.6924765936},
{"learn":[0.003206161757],"iteration":576,"passed_time":0.9419495353,"remaining_time":0.6905453266},
{"learn":[0.003206169065],"iteration":577,"passed_time":0.9432236399,"remaining_time":0.6886511696},
{"learn":[0.003206169343],"iteration":578,"passed_time":0.9444430349,"remaining_time":0.6867193742},
{"learn":[0.003206168233],"iteration":579,"passed_time":0.9456620336,"remaining_time":0.6847897484},
{"learn":[0.003206158621],"iteration":580,"passed_time":0.946885854,"remaining_time":0.6828660462},
{"learn":[0.003206155292],"iteration":581,"passed_time":0.9482171357,"remaining_time":0.681021929},
{"learn":[0.003195674246],"iteration":582,"passed_time":0.9495761592,"remaining_time":0.679199414},
{"learn":[0.003187977183],"iteration":583,"passed_time":0.9509619027,"remaining_time":0.6773975198},
{"learn":[0.003182548421],"iteration":584,"passed_time":0.952303163,"remaining_time":0.6755654917},
{"learn":[0.003182541764],"iteration":585,"passed_time":0.9534814282,"remaining_time":0.6736199851},
{"learn":[0.003182543524],"iteration":586,"passed_time":0.9547100778,"remaining_time":0.6717125419},
{"learn":[0.00318250007],"iteration":587,"passed_time":0.9559353237,"remaining_time":0.6698050227},
{"learn":[0.003182458183],"iteration":588,"passed_time":0.9571793893,"remaining_time":0.6679129525},
{"learn":[0.003175539473],"iteration":589,"passed_time":0.9585784979,"remaining_time":0.6661308205},
{"learn":[0.003167898482],"iteration":590,"passed_time":0.9599487251,"remaining_time":0.6643299976},
{"learn":[0.003167820581],"iteration":591,"passed_time":0.9611877713,"remaining_time":0.6624402208},
{"learn":[0.003158346601],"iteration":592,"passed_time":0.9625635791,"remaining_time":0.6606465037},
{"learn":[0.00314657653],"iteration":593,"passed_time":0.9641131743,"remaining_time":0.6589729777},
{"learn":[0.003146583091],"iteration":594,"passed_time":0.9654803853,"remaining_time":0.6571757245},
{"learn":[0.003146553698],"iteration":595,"passed_time":0.9667861993,"remaining_time":0.6553382962},
{"learn":[0.003144400303],"iteration":596,"passed_time":0.9680691004,"remaining_time":0.6534871816},
{"learn":[0.003140530591],"iteration":597,"passed_time":0.9693540753,"remaining_time":0.6516393617},
{"learn":[0.003133457084],"iteration":598,"passed_time":0.9707293392,"remaining_time":0.6498538648},
{"learn":[0.003133269594],"iteration":599,"passed_time":0.9719620463,"remaining_time":0.6479746976},
{"learn":[0.003133236307],"iteration":600,"passed_time":0.9731512821,"remaining_time":0.6460688212},
{"learn":[0.003133235016],"iteration":601,"passed_time":0.9743462085,"remaining_time":0.644169088},
{"learn":[0.003125860476],"iteration":602,"passed_time":0.9757129966,"remaining_time":0.6423848419},
{"learn":[0.003123960008],"iteration":603,"passed_time":0.9769442911,"remaining_time":0.6405131445},
{"learn":[0.003123941796],"iteration":604,"passed_time":0.9782335919,"remaining_time":0.638681436},
{"learn":[0.003117410288],"iteration":605,"passed_time":0.979612585,"remaining_time":0.6369098325},
{"learn":[0.003105059657],"iteration":606,"passed_time":0.9809646555,"remaining_time":0.6351220916},
{"learn":[0.003093295967],"iteration":607,"passed_time":0.9823094524,"remaining_time":0.6333310943},
{"learn":[0.003088660519],"iteration":608,"passed_time":0.9836069207,"remaining_time":0.6315111757},
{"learn":[0.00308838748],"iteration":609,"passed_time":0.9848259423,"remaining_time":0.6296428155},
{"learn":[0.00307795338],"iteration":610,"passed_time":0.9861838237,"remaining_time":0.6278649876},
{"learn":[0.003064780594],"iteration":611,"passed_time":0.9875436515,"remaining_time":0.626089766},
{"learn":[0.003053988924],"iteration":612,"passed_time":0.9889182113,"remaining_time":0.6243252003},
{"learn":[0.003040772856],"iteration":613,"passed_time":0.9902936455,"remaining_time":0.6225624547},
{"learn":[0.003036030572],"iteration":614,"passed_time":0.9916389762,"remaining_time":0.6207821233},
{"learn":[0.003028309172],"iteration":615,"passed_time":0.9929888198,"remaining_time":0.6190060175},
{"learn":[0.003028260447],"iteration":616,"passed_time":0.9943372162,"remaining_time":0.6172303952},
{"learn":[0.003022264631],"iteration":617,"passed_time":0.9957011061,"remaining_time":0.6154657322},
{"learn":[0.003011386959],"iteration":618,"passed_time":0.9970781934,"remaining_time":0.6137104874},
{"learn":[0.002999740088],"iteration":619,"passed_time":0.9984606185,"remaining_time":0.6119597339},
{"learn":[0.002999745358],"iteration":620,"passed_time":0.9996858138,"remaining_time":0.6101142084},
{"learn":[0.002999725109],"iteration":621,"passed_time":1.000899636,"remaining_time":0.6082637657},
{"learn":[0.002999706246],"iteration":622,"passed_time":1.002131401,"remaining_time":0.606426225},
{"learn":[0.002998148906],"iteration":623,"passed_time":1.003396489,"remaining_time":0.6046107047},
{"learn":[0.002998094911],"iteration":624,"passed_time":1.004595823,"remaining_time":0.602757494},
{"learn":[0.002998094079],"iteration":625,"passed_time":1.005751947,"remaining_time":0.6008805563},
{"learn":[0.002993727847],"iteration":626,"passed_time":1.00712129,"remaining_time":0.599132761},
{"learn":[0.002987719024],"iteration":627,"passed_time":1.008549406,"remaining_time":0.5974209855},
{"learn":[0.002983577699],"iteration":628,"passed_time":1.009927505,"remaining_time":0.5956806109},
{"learn":[0.002979013931],"iteration":629,"passed_time":1.011253013,"remaining_time":0.5939104996},
{"learn":[0.002969934532],"iteration":630,"passed_time":1.01261948,"remaining_time":0.59216575},
{"learn":[0.002962148689],"iteration":631,"passed_time":1.013984675,"remaining_time":0.5904214566},
{"learn":[0.002954935325],"iteration":632,"passed_time":1.015313903,"remaining_time":0.5886575078},
{"learn":[0.002954918607],"iteration":633,"passed_time":1.016542362,"remaining_time":0.5868367581},
{"learn":[0.002954691097],"iteration":634,"passed_time":1.0177435,"remaining_time":0.5850021695},
{"learn":[0.002954290639],"iteration":635,"passed_time":1.018946061,"remaining_time":0.5831703871},
{"learn":[0.002954276588],"iteration":636,"passed_time":1.02008339,"remaining_time":0.5813034073},
{"learn":[0.00294382861],"iteration":637,"passed_time":1.021460106,"remaining_time":0.5795745431},
{"learn":[0.002934914564],"iteration":638,"passed_time":1.022795719,"remaining_time":0.5778235595},
{"learn":[0.002934870097],"iteration":639,"passed_time":1.024078226,"remaining_time":0.5760440023},
{"learn":[0.002934796865],"iteration":640,"passed_time":1.025501688,"remaining_time":0.574344939},
{"learn":[0.002934788266],"iteration":641,"passed_time":1.0268388,"remaining_time":0.5725985833},
{"learn":[0.002934797697],"iteration":642,"passed_time":1.028167958,"remaining_time":0.5708490839},
{"learn":[0.00293479631],"iteration":643,"passed_time":1.029447959,"remaining_time":0.5690737165},
{"learn":[0.002932996835],"iteration":644,"passed_time":1.03077345,"remaining_time":0.567324922},
{"learn":[0.002932990177],"iteration":645,"passed_time":1.031991557,"remaining_time":0.5655185931},
{"learn":[0.002932982784],"iteration":646,"passed_time":1.033185562,"remaining_time":0.5637009323},
{"learn":[0.002932966876],"iteration":647,"passed_time":1.034368676,"remaining_time":0.5618792807},
{"learn":[0.002932978057],"iteration":648,"passed_time":1.035571647,"remaining_time":0.5600703362},
{"learn":[0.002927980321],"iteration":649,"passed_time":1.036948805,"remaining_time":0.5583570487},
{"learn":[0.002927929558],"iteration":650,"passed_time":1.038174449,"remaining_time":0.5565635677},
{"learn":[0.002927891001],"iteration":651,"passed_time":1.039463609,"remaining_time":0.5548057301},
{"learn":[0.002927899877],"iteration":652,"passed_time":1.040707459,"remaining_time":0.5530252503},
{"learn":[0.002927896271],"iteration":653,"passed_time":1.04190871,"remaining_time":0.5512238743},
{"learn":[0.002927901542],"iteration":654,"passed_time":1.043086903,"remaining_time":0.5494121854},
{"learn":[0.002927822943],"iteration":655,"passed_time":1.044274899,"remaining_time":0.547607569},
{"learn":[0.002927808519],"iteration":656,"passed_time":1.045445748,"remaining_time":0.5457958773},
{"learn":[0.002923587485],"iteration":657,"passed_time":1.046702369,"remaining_time":0.5440307148},
{"learn":[0.002919728052],"iteration":658,"passed_time":1.04799044,"remaining_time":0.5422833689},
{"learn":[0.002919693474],"iteration":659,"passed_time":1.049180658,"remaining_time":0.5404870055},
{"learn":[0.002914626271],"iteration":660,"passed_time":1.050556162,"remaining_time":0.5387875022},
{"learn":[0.002906441916],"iteration":661,"passed_time":1.051912844,"remaining_time":0.5370793675},
{"learn":[0.002906441916],"iteration":662,"passed_time":1.053049859,"remaining_time":0.5352606374},
{"learn":[0.002906440781],"iteration":663,"passed_time":1.054195924,"remaining_time":0.53344854},
{"learn":[0.002893564171],"iteration":664,"passed_time":1.05576981,"remaining_time":0.5318539644},
{"learn":[0.002883587656],"iteration":665,"passed_time":1.057265469,"remaining_time":0.5302202203},
{"learn":[0.002881660169],"iteration":666,"passed_time":1.058657875,"remaining_time":0.528535341},
{"learn":[0.002881591931],"iteration":667,"passed_time":1.05996954,"remaining_time":0.5268112086},
{"learn":[0.002875292188],"iteration":668,"passed_time":1.061348892,"remaining_time":0.5251217984},
{"learn":[0.002870899258],"iteration":669,"passed_time":1.062732111,"remaining_time":0.5234352186},
{"learn":[0.002870824169],"iteration":670,"passed_time":1.063969036,"remaining_time":0.5216778132},
{"learn":[0.002870836929],"iteration":671,"passed_time":1.065123176,"remaining_time":0.51988155},
{"learn":[0.002868416708],"iteration":672,"passed_time":1.066369218,"remaining_time":0.5181318487},
{"learn":[0.002868416708],"iteration":673,"passed_time":1.067571959,"remaining_time":0.5163626981},
{"learn":[0.002868297911],"iteration":674,"passed_time":1.068781142,"remaining_time":0.5145983275},
{"learn":[0.002866419336],"iteration":675,"passed_time":1.07012674,"remaining_time":0.512900982},
{"learn":[0.002856219167],"iteration":676,"passed_time":1.071473501,"remaining_time":0.5112052301},
{"learn":[0.002856205852],"iteration":677,"passed_time":1.072676312,"remaining_time":0.5094421423},
{"learn":[0.002856200955],"iteration":678,"passed_time":1.073864195,"remaining_time":0.5076736475},
{"learn":[0.002856055648],"iteration":679,"passed_time":1.075063219,"remaining_time":0.5059121032},
{"learn":[0.002855947695],"iteration":680,"passed_time":1.076291538,"remaining_time":0.5041659334},
{"learn":[0.002849373516],"iteration":681,"passed_time":1.077626427,"remaining_time":0.5024709731},
{"learn":[0.002839682442],"iteration":682,"passed_time":1.078976025,"remaining_time":0.5007838946},
{"learn":[0.002828306995],"iteration":683,"passed_time":1.080356316,"remaining_time":0.4991119821},
{"learn":[0.002828277495],"iteration":684,"passed_time":1.081581148,"remaining_time":0.4973694331},
{"learn":[0.002828280824],"iteration":685,"passed_time":1.082758492,"remaining_time":0.4956066565},
{"learn":[0.002828281934],"iteration":686,"passed_time":1.083944141,"remaining_time":0.4938493683},
{"learn":[0.002820886524],"iteration":687,"passed_time":1.085341323,"remaining_time":0.4921896699},
{"learn":[0.00282088662],"iteration":688,"passed_time":1.086571157,"remaining_time":0.4904551959},
{"learn":[0.0028160308],"iteration":689,"passed_time":1.087903641,"remaining_time":0.4887683026},
{"learn":[0.002816028581],"iteration":690,"passed_time":1.089066979,"remaining_time":0.4870067965},
{"learn":[0.002816010091],"iteration":691,"passed_time":1.090262246,"remaining_time":0.4852612307},
{"learn":[0.002815970894],"iteration":692,"passed_time":1.091452626,"remaining_time":0.4835150884},
{"learn":[0.002815783654],"iteration":693,"passed_time":1.092657498,"remaining_time":0.4817769374},
{"learn":[0.002813649628],"iteration":694,"passed_time":1.093876911,"remaining_time":0.4800467018},
{"learn":[0.002813650002],"iteration":695,"passed_time":1.095074803,"remaining_time":0.4783085345},
{"learn":[0.002813650002],"iteration":696,"passed_time":1.096225055,"remaining_time":0.4765512078},
{"learn":[0.002813631971],"iteration":697,"passed_time":1.09736559,"remaining_time":0.4747914158},
{"learn":[0.002813595174],"iteration":698,"passed_time":1.098566227,"remaining_time":0.4730592767},
{"learn":[0.002813480938],"iteration":699,"passed_time":1.09982356,"remaining_time":0.4713529545},
{"learn":[0.002813356232],"iteration":700,"passed_time":1.101147478,"remaining_time":0.4696763138},
{"learn":[0.002813345329],"iteration":701,"passed_time":1.102331474,"remaining_time":0.4679412811},
{"learn":[0.002813343014],"iteration":702,"passed_time":1.103555846,"remaining_time":0.4662248737},
{"learn":[0.002813346161],"iteration":703,"passed_time":1.104759599,"remaining_time":0.4645011949},
{"learn":[0.002806891347],"iteration":704,"passed_time":1.106106139,"remaining_time":0.4628387389},
{"learn":[0.002806891347],"iteration":705,"passed_time":1.107299856,"remaining_time":0.4611135377},
{"learn":[0.002806888669],"iteration":706,"passed_time":1.108506351,"remaining_time":0.4593951356},
{"learn":[0.002800643483],"iteration":707,"passed_time":1.109893527,"remaining_time":0.4577526977},
{"learn":[0.002793721802],"iteration":708,"passed_time":1.11129337,"remaining_time":0.4561161786},
{"learn":[0.002790194721],"iteration":709,"passed_time":1.112586149,"remaining_time":0.4544365963},
{"learn":[0.002790179464],"iteration":710,"passed_time":1.11376316,"remaining_time":0.4527110452},
{"learn":[0.00279015866],"iteration":711,"passed_time":1.114947639,"remaining_time":0.4509900563},
{"learn":[0.00279014479],"iteration":712,"passed_time":1.116241992,"remaining_time":0.4493147989},
{"learn":[0.002790159119],"iteration":713,"passed_time":1.117464617,"remaining_time":0.4476118775},
{"learn":[0.002789856313],"iteration":714,"passed_time":1.118681565,"remaining_time":0.4459080363},
{"learn":[0.002789850488],"iteration":715,"passed_time":1.119876642,"remaining_time":0.4441968802},
{"learn":[0.002789835509],"iteration":716,"passed_time":1.121053274,"remaining_time":0.4424798835},
{"learn":[0.002789735851],"iteration":717,"passed_time":1.122266564,"remaining_time":0.4407787899},
{"learn":[0.002789717991],"iteration":718,"passed_time":1.123469927,"remaining_time":0.439075173},
{"learn":[0.002785550915],"iteration":719,"passed_time":1.124806278,"remaining_time":0.4374246636},
{"learn":[0.002785542594],"iteration":720,"passed_time":1.125969144,"remaining_time":0.4357078935},
{"learn":[0.002784833664],"iteration":721,"passed_time":1.127228631,"remaining_time":0.4340298608},
{"learn":[0.00278077681],"iteration":722,"passed_time":1.128456089,"remaining_time":0.4323407145},
{"learn":[0.002780664828],"iteration":723,"passed_time":1.129692352,"remaining_time":0.4306562007},
{"learn":[0.002780638199],"iteration":724,"passed_time":1.130847464,"remaining_time":0.4289421417},
{"learn":[0.002780619155],"iteration":725,"passed_time":1.132141209,"remaining_time":0.4272819437},
{"learn":[0.002780617309],"iteration":726,"passed_time":1.133338416,"remaining_time":0.425586503},
{"learn":[0.002780603802],"iteration":727,"passed_time":1.134564441,"remaining_time":0.4239031977},
{"learn":[0.002780601028],"iteration":728,"passed_time":1.135786679,"remaining_time":0.4222197392},
{"learn":[0.002780517918],"iteration":729,"passed_time":1.136988861,"remaining_time":0.4205301268},
{"learn":[0.002778778133],"iteration":730,"passed_time":1.13826134,"remaining_time":0.4188677161},
{"learn":[0.002772432052],"iteration":731,"passed_time":1.139668704,"remaining_time":0.4172557551},
{"learn":[0.002772442845],"iteration":732,"passed_time":1.140869655,"remaining_time":0.4155691648},
{"learn":[0.002770094767],"iteration":733,"passed_time":1.142141502,"remaining_time":0.4139095907},
{"learn":[0.002769440308],"iteration":734,"passed_time":1.143413914,"remaining_time":0.412251275},
{"learn":[0.002769433096],"iteration":735,"passed_time":1.144630433,"remaining_time":0.4105739597},
{"learn":[0.002769357357],"iteration":736,"passed_time":1.145866123,"remaining_time":0.4089047359},
{"learn":[0.002769341642],"iteration":737,"passed_time":1.147119429,"remaining_time":0.4072429408},
{"learn":[0.00276934895],"iteration":738,"passed_time":1.148351064,"remaining_time":0.4055745977},
{"learn":[0.002769339796],"iteration":739,"passed_time":1.149530584,"remaining_time":0.4038891242},
{"learn":[0.002769219457],"iteration":740,"passed_time":1.150744604,"remaining_time":0.4022170747},
{"learn":[0.002769222352],"iteration":741,"passed_time":1.151931094,"remaining_time":0.4005366878},
{"learn":[0.002769214585],"iteration":742,"passed_time":1.153119298,"remaining_time":0.3988582229},
{"learn":[0.002769139423],"iteration":743,"passed_time":1.154348519,"remaining_time":0.3971951892},
{"learn":[0.002769104749],"iteration":744,"passed_time":1.155522759,"remaining_time":0.3955145015},
{"learn":[0.002769108248],"iteration":745,"passed_time":1.156683041,"remaining_time":0.3938304187},
{"learn":[0.002769042421],"iteration":746,"passed_time":1.157897631,"remaining_time":0.3921661321},
{"learn":[0.002768752615],"iteration":747,"passed_time":1.159070406,"remaining_time":0.3904889603},
{"learn":[0.002768736623],"iteration":748,"passed_time":1.160257731,"remaining_time":0.3888180113},
{"learn":[0.00276365984],"iteration":749,"passed_time":1.161646197,"remaining_time":0.387215399},
{"learn":[0.002763459994],"iteration":750,"passed_time":1.162973764,"remaining_time":0.3855931655},
{"learn":[0.002763131936],"iteration":751,"passed_time":1.164296657,"remaining_time":0.3839701743},
{"learn":[0.0027630513],"iteration":752,"passed_time":1.165573086,"remaining_time":0.3823327388},
{"learn":[0.002763009595],"iteration":753,"passed_time":1.166737846,"remaining_time":0.3806598279},
{"learn":[0.002762872914],"iteration":754,"passed_time":1.167908067,"remaining_time":0.3789900348},
{"learn":[0.00275093124],"iteration":755,"passed_time":1.169254937,"remaining_time":0.3773785777},
{"learn":[0.00273932942],"iteration":756,"passed_time":1.170635892,"remaining_time":0.3757787605},
{"learn":[0.002730591646],"iteration":757,"passed_time":1.172021886,"remaining_time":0.3741811298},
{"learn":[0.002730489266],"iteration":758,"passed_time":1.173268171,"remaining_time":0.372539696},
{"learn":[0.002730466979],"iteration":759,"passed_time":1.174451744,"remaining_time":0.370879498},
{"learn":[0.002730466979],"iteration":760,"passed_time":1.175651529,"remaining_time":0.3692256445},
{"learn":[0.002730467534],"iteration":761,"passed_time":1.176793226,"remaining_time":0.3675548396},
{"learn":[0.002730307863],"iteration":762,"passed_time":1.178216492,"remaining_time":0.3659728817},
{"learn":[0.002730316462],"iteration":763,"passed_time":1.17955238,"remaining_time":0.3643643477},
{"learn":[0.002730300373],"iteration":764,"passed_time":1.180831344,"remaining_time":0.3627390402},
{"learn":[0.00273030176],"iteration":765,"passed_time":1.182070576,"remaining_time":0.3611024996},
{"learn":[0.002730286781],"iteration":766,"passed_time":1.183268826,"remaining_time":0.3594545454},
{"learn":[0.002730227526],"iteration":767,"passed_time":1.184474682,"remaining_time":0.3578100603},
{"learn":[0.002730191864],"iteration":768,"passed_time":1.185644051,"remaining_time":0.3561557552},
{"learn":[0.002730133889],"iteration":769,"passed_time":1.18683373,"remaining_time":0.3545087766},
{"learn":[0.002730110588],"iteration":770,"passed_time":1.188027084,"remaining_time":0.3528640755},
{"learn":[0.002727826868],"iteration":771,"passed_time":1.189345709,"remaining_time":0.351257541},
{"learn":[0.002717867352],"iteration":772,"passed_time":1.190718882,"remaining_time":0.3496677699},
{"learn":[0.00271259642],"iteration":773,"passed_time":1.192056776,"remaining_time":0.3480682575},
{"learn":[0.002705979539],"iteration":774,"passed_time":1.193548856,"remaining_time":0.3465141839},
{"learn":[0.00270592406],"iteration":775,"passed_time":1.194762677,"remaining_time":0.3448799481},
{"learn":[0.002705869233],"iteration":776,"passed_time":1.195905877,"remaining_time":0.3432265258},
{"learn":[0.00269720773],"iteration":777,"passed_time":1.197278376,"remaining_time":0.341639845},
{"learn":[0.002697194597],"iteration":778,"passed_time":1.198473512,"remaining_time":0.340003397},
{"learn":[0.002697181005],"iteration":779,"passed_time":1.199675462,"remaining_time":0.3383700021},
{"learn":[0.002697173515],"iteration":780,"passed_time":1.200891621,"remaining_time":0.3367416965},
{"learn":[0.002696966122],"iteration":781,"passed_time":1.202149165,"remaining_time":0.3351259819},
{"learn":[0.002696963903],"iteration":782,"passed_time":1.203320945,"remaining_time":0.3334874138},
{"learn":[0.002696963625],"iteration":783,"passed_time":1.204519658,"remaining_time":0.3318574569},
{"learn":[0.002696965567],"iteration":784,"passed_time":1.205735905,"remaining_time":0.3302334006},
{"learn":[0.002696846481],"iteration":785,"passed_time":1.206978641,"remaining_time":0.3286175943},
{"learn":[0.002692916053],"iteration":786,"passed_time":1.208300725,"remaining_time":0.3270242115},
{"learn":[0.002692902183],"iteration":787,"passed_time":1.20951082,"remaining_time":0.3254013881},
{"learn":[0.00269291282],"iteration":788,"passed_time":1.210717027,"remaining_time":0.3237785713},
{"learn":[0.002692897841],"iteration":789,"passed_time":1.211896104,"remaining_time":0.3221495973},
{"learn":[0.002692878701],"iteration":790,"passed_time":1.213098855,"remaining_time":0.3205280161},
{"learn":[0.002692885081],"iteration":791,"passed_time":1.214258315,"remaining_time":0.3188961232},
{"learn":[0.002689976645],"iteration":792,"passed_time":1.215538173,"remaining_time":0.3172968498},
{"learn":[0.002689985148],"iteration":793,"passed_time":1.216733127,"remaining_time":0.3156763528},
{"learn":[0.002689902293],"iteration":794,"passed_time":1.217932532,"remaining_time":0.3140580742},
{"learn":[0.002689913026],"iteration":795,"passed_time":1.21908025,"remaining_time":0.3124276017},
{"learn":[0.002689900821],"iteration":796,"passed_time":1.220269235,"remaining_time":0.3108088516},
{"learn":[0.002689884167],"iteration":797,"passed_time":1.22145819,"remaining_time":0.309191171},
{"learn":[0.002689889437],"iteration":798,"passed_time":1.222637528,"remaining_time":0.307572144},
{"learn":[0.002685848282],"iteration":799,"passed_time":1.224086492,"remaining_time":0.306021623},
{"learn":[0.002684786297],"iteration":800,"passed_time":1.225359021,"remaining_time":0.3044275221},
{"learn":[0.002678308538],"iteration":801,"passed_time":1.226735828,"remaining_time":0.3028599675},
{"learn":[0.002666264446],"iteration":802,"passed_time":1.228117276,"remaining_time":0.3012940267},
{"learn":[0.002660802728],"iteration":803,"passed_time":1.229462922,"remaining_time":0.2997198168},
{"learn":[0.002660776472],"iteration":804,"passed_time":1.23068527,"remaining_time":0.2981163075},
{"learn":[0.002659080021],"iteration":805,"passed_time":1.231983682,"remaining_time":0.2965320526},
{"learn":[0.002656178205],"iteration":806,"passed_time":1.233262744,"remaining_time":0.294943878},
{"learn":[0.002656172753],"iteration":807,"passed_time":1.234491804,"remaining_time":0.2933445871},
{"learn":[0.002656168315],"iteration":808,"passed_time":1.235691412,"remaining_time":0.2917392579},
{"learn":[0.002656168315],"iteration":809,"passed_time":1.236858273,"remaining_time":0.2901272492},
{"learn":[0.002656168315],"iteration":810,"passed_time":1.237995341,"remaining_time":0.2885093951},
{"learn":[0.002656154722],"iteration":811,"passed_time":1.239424549,"remaining_time":0.2869603635},
{"learn":[0.002656074268],"iteration":812,"passed_time":1.240748386,"remaining_time":0.2853873902},
{"learn":[0.002656078706],"iteration":813,"passed_time":1.241944142,"remaining_time":0.2837857621},
{"learn":[0.002655586879],"iteration":814,"passed_time":1.24322545,"remaining_time":0.2822045499},
{"learn":[0.002655443659],"iteration":815,"passed_time":1.244475179,"remaining_time":0.280616952},
{"learn":[0.002655453827],"iteration":816,"passed_time":1.245693719,"remaining_time":0.2790231954},
{"learn":[0.0026554247],"iteration":817,"passed_time":1.246920345,"remaining_time":0.277432155},
{"learn":[0.002655432009],"iteration":818,"passed_time":1.248112158,"remaining_time":0.2758343109},
{"learn":[0.002654657467],"iteration":819,"passed_time":1.249373198,"remaining_time":0.2742526533},
{"learn":[0.002646792807],"iteration":820,"passed_time":1.250753131,"remaining_time":0.2726976985},
{"learn":[0.002646797245],"iteration":821,"passed_time":1.251978515,"remaining_time":0.2711097027},
{"learn":[0.002646746205],"iteration":822,"passed_time":1.253150318,"remaining_time":0.2695110647},
{"learn":[0.002646746205],"iteration":823,"passed_time":1.254432284,"remaining_time":0.2679369927},
{"learn":[0.002646710614],"iteration":824,"passed_time":1.255678076,"remaining_time":0.2663559555},
{"learn":[0.002646628506],"iteration":825,"passed_time":1.256868985,"remaining_time":0.2647641687},
{"learn":[0.002646578394],"iteration":826,"passed_time":1.258064462,"remaining_time":0.2631743071},
{"learn":[0.002646549727],"iteration":827,"passed_time":1.259288693,"remaining_time":0.2615913711},
{"learn":[0.002646538076],"iteration":828,"passed_time":1.260478951,"remaining_time":0.2600022927},
{"learn":[0.002646516162],"iteration":829,"passed_time":1.261691821,"remaining_time":0.2584188067},
{"learn":[0.002646395582],"iteration":830,"passed_time":1.262911514,"remaining_time":0.2568376003},
{"learn":[0.00264634101],"iteration":831,"passed_time":1.264097634,"remaining_time":0.2552504837},
{"learn":[0.0026463289],"iteration":832,"passed_time":1.265290169,"remaining_time":0.253665616},
{"learn":[0.002646263314],"iteration":833,"passed_time":1.266660102,"remaining_time":0.2521169988},
{"learn":[0.002646208742],"iteration":834,"passed_time":1.267963209,"remaining_time":0.2505556041},
{"learn":[0.002646163539],"iteration":835,"passed_time":1.269257759,"remaining_time":0.2489931489},
{"learn":[0.002638954024],"iteration":836,"passed_time":1.270785624,"remaining_time":0.2474767702},
{"learn":[0.00263353346],"iteration":837,"passed_time":1.272158864,"remaining_time":0.2459304725},
{"learn":[0.002633527912],"iteration":838,"passed_time":1.273432555,"remaining_time":0.2443654843},
{"learn":[0.002633505625],"iteration":839,"passed_time":1.27471763,"remaining_time":0.2428033581},
{"learn":[0.002633505625],"iteration":840,"passed_time":1.275974425,"remaining_time":0.2412365441},
{"learn":[0.002633512101],"iteration":841,"passed_time":1.277229354,"remaining_time":0.2396701163},
{"learn":[0.002632292295],"iteration":842,"passed_time":1.278551105,"remaining_time":0.2381168724},
{"learn":[0.002622910579],"iteration":843,"passed_time":1.279961274,"remaining_time":0.2365805198},
{"learn":[0.002622891439],"iteration":844,"passed_time":1.281199401,"remaining_time":0.2350129079},
{"learn":[0.00262286674],"iteration":845,"passed_time":1.28241703,"remaining_time":0.2334423435},
{"learn":[0.002622821248],"iteration":846,"passed_time":1.283622586,"remaining_time":0.2318704318},
{"learn":[0.002622739236],"iteration":847,"passed_time":1.285001109,"remaining_time":0.2303303875},
{"learn":[0.002622749126],"iteration":848,"passed_time":1.286214227,"remaining_time":0.2287613054},
{"learn":[0.00262274839],"iteration":849,"passed_time":1.287417759,"remaining_time":0.2271913693},
{"learn":[0.002622747184],"iteration":850,"passed_time":1.288612809,"remaining_time":0.2256208091},
{"learn":[0.002622670105],"iteration":851,"passed_time":1.289817631,"remaining_time":0.2240528279},
{"learn":[0.0026226579],"iteration":852,"passed_time":1.291020562,"remaining_time":0.2224853724},
{"learn":[0.002620731603],"iteration":853,"passed_time":1.292290599,"remaining_time":0.220930243},
{"learn":[0.002612236201],"iteration":854,"passed_time":1.293669941,"remaining_time":0.2193943175},
{"learn":[0.0026122215],"iteration":855,"passed_time":1.294900694,"remaining_time":0.2178337617},
{"learn":[0.002612223996],"iteration":856,"passed_time":1.29614335,"remaining_time":0.2162759616},
{"learn":[0.002611075469],"iteration":857,"passed_time":1.297454647,"remaining_time":0.2147302563},
{"learn":[0.002611075469],"iteration":858,"passed_time":1.298644083,"remaining_time":0.213165094},
{"learn":[0.002610275145],"iteration":859,"passed_time":1.299994657,"remaining_time":0.2116270372},
{"learn":[0.002610281717],"iteration":860,"passed_time":1.301291586,"remaining_time":0.2100807554},
{"learn":[0.002610241314],"iteration":861,"passed_time":1.302507111,"remaining_time":0.20852202},
{"learn":[0.002610241314],"iteration":862,"passed_time":1.30371307,"remaining_time":0.2069625616},
{"learn":[0.002610241314],"iteration":863,"passed_time":1.304883698,"remaining_time":0.2053983599},
{"learn":[0.002606421096],"iteration":864,"passed_time":1.306220801,"remaining_time":0.2038610499},
{"learn":[0.002594970625],"iteration":865,"passed_time":1.30758111,"remaining_time":0.202327793},
{"learn":[0.002594968683],"iteration":866,"passed_time":1.308787688,"remaining_time":0.2007713524},
{"learn":[0.002594902977],"iteration":867,"passed_time":1.309964921,"remaining_time":0.1992112553},
{"learn":[0.002594897707],"iteration":868,"passed_time":1.311175093,"remaining_time":0.1976570049},
{"learn":[0.002592595565],"iteration":869,"passed_time":1.312528266,"remaining_time":0.1961249133},
{"learn":[0.002592590657],"iteration":870,"passed_time":1.313726178,"remaining_time":0.1945702376},
{"learn":[0.002592476335],"iteration":871,"passed_time":1.315036333,"remaining_time":0.1930328562},
{"learn":[0.002592459692],"iteration":872,"passed_time":1.316291599,"remaining_time":0.1914880104},
{"learn":[0.00259246524],"iteration":873,"passed_time":1.31748868,"remaining_time":0.189935439},
{"learn":[0.002592436946],"iteration":874,"passed_time":1.318690128,"remaining_time":0.1883843041},
{"learn":[0.002592449646],"iteration":875,"passed_time":1.319931432,"remaining_time":0.186839609},
{"learn":[0.002592348301],"iteration":876,"passed_time":1.32112751,"remaining_time":0.1852892631},
{"learn":[0.002592268423],"iteration":877,"passed_time":1.322312468,"remaining_time":0.1837381789},
{"learn":[0.002592268146],"iteration":878,"passed_time":1.323526871,"remaining_time":0.1821919811},
{"learn":[0.002592257882],"iteration":879,"passed_time":1.324744009,"remaining_time":0.1806469103},
{"learn":[0.00259225067],"iteration":880,"passed_time":1.32598443,"remaining_time":0.179105729},
{"learn":[0.002592273971],"iteration":881,"passed_time":1.327236333,"remaining_time":0.1775667657},
{"learn":[0.002592251044],"iteration":882,"passed_time":1.328490433,"remaining_time":0.1760287437},
{"learn":[0.002592180597],"iteration":883,"passed_time":1.329855608,"remaining_time":0.1745059396},
{"learn":[0.002586899119],"iteration":884,"passed_time":1.331244144,"remaining_time":0.1729865272},
{"learn":[0.002586604081],"iteration":885,"passed_time":1.332444781,"remaining_time":0.1714432337},
{"learn":[0.00258660103],"iteration":886,"passed_time":1.333648795,"remaining_time":0.169901143},
{"learn":[0.00258653852],"iteration":887,"passed_time":1.334872756,"remaining_time":0.1683623295},
{"learn":[0.002586264542],"iteration":888,"passed_time":1.336102567,"remaining_time":0.166824955},
{"learn":[0.002586256498],"iteration":889,"passed_time":1.337317131,"remaining_time":0.1652863869},
{"learn":[0.002586233293],"iteration":890,"passed_time":1.338557873,"remaining_time":0.1637517487},
{"learn":[0.002586221088],"iteration":891,"passed_time":1.33978021,"remaining_time":0.1622155412},
{"learn":[0.002586214345],"iteration":892,"passed_time":1.341005777,"remaining_time":0.1606804234},
{"learn":[0.002586230796],"iteration":893,"passed_time":1.342192094,"remaining_time":0.1591413445},
{"learn":[0.002586230796],"iteration":894,"passed_time":1.343340905,"remaining_time":0.1575986536},
{"learn":[0.002586205554],"iteration":895,"passed_time":1.34470459,"remaining_time":0.1560817827},
{"learn":[0.00258618891],"iteration":896,"passed_time":1.346094706,"remaining_time":0.1545682885},
{"learn":[0.002585820336],"iteration":897,"passed_time":1.347447631,"remaining_time":0.1530508445},
{"learn":[0.002585798155],"iteration":898,"passed_time":1.34880573,"remaining_time":0.1515343479},
{"learn":[0.00258517582],"iteration":899,"passed_time":1.350233064,"remaining_time":0.150025896},
{"learn":[0.002585048774],"iteration":900,"passed_time":1.351645668,"remaining_time":0.1485160057},
{"learn":[0.002582556609],"iteration":901,"passed_time":1.352965618,"remaining_time":0.1469962645},
{"learn":[0.002578012678],"iteration":902,"passed_time":1.35442547,"remaining_time":0.145491994},
{"learn":[0.002570944753],"iteration":903,"passed_time":1.355892726,"remaining_time":0.1439886081},
{"learn":[0.002570942257],"iteration":904,"passed_time":1.357165571,"remaining_time":0.1424648942},
{"learn":[0.002570171299],"iteration":905,"passed_time":1.358719948,"remaining_time":0.1409709438},
{"learn":[0.00257017546],"iteration":906,"passed_time":1.360003543,"remaining_time":0.1394490954},
{"learn":[0.002570154004],"iteration":907,"passed_time":1.361320949,"remaining_time":0.1379311974},
{"learn":[0.002569392557],"iteration":908,"passed_time":1.362702542,"remaining_time":0.1364201664},
{"learn":[0.002560638268],"iteration":909,"passed_time":1.364173104,"remaining_time":0.1349182191},
{"learn":[0.00255479674],"iteration":910,"passed_time":1.365593833,"remaining_time":0.1334114721},
{"learn":[0.002554756433],"iteration":911,"passed_time":1.366848842,"remaining_time":0.1318889233},
{"learn":[0.002554763741],"iteration":912,"passed_time":1.368008525,"remaining_time":0.130357877},
{"learn":[0.002554704849],"iteration":913,"passed_time":1.369224979,"remaining_time":0.1288329849},
{"learn":[0.002554672394],"iteration":914,"passed_time":1.370428121,"remaining_time":0.1273075303},
{"learn":[0.002554670452],"iteration":915,"passed_time":1.371624981,"remaining_time":0.1257822035},
{"learn":[0.002554649563],"iteration":916,"passed_time":1.372844213,"remaining_time":0.1242596179},
{"learn":[0.002554607207],"iteration":917,"passed_time":1.374154705,"remaining_time":0.1227458451},
{"learn":[0.002554582156],"iteration":918,"passed_time":1.375386373,"remaining_time":0.1212255672},
{"learn":[0.002554602683],"iteration":919,"passed_time":1.376568586,"remaining_time":0.1197016162},
{"learn":[0.0025545988],"iteration":920,"passed_time":1.377757428,"remaining_time":0.1181789759},
{"learn":[0.002554582989],"iteration":921,"passed_time":1.378971621,"remaining_time":0.1166592043},
{"learn":[0.002554574667],"iteration":922,"passed_time":1.380117037,"remaining_time":0.1151343574},
{"learn":[0.002554578273],"iteration":923,"passed_time":1.381333782,"remaining_time":0.1136161985},
{"learn":[0.002546820285],"iteration":924,"passed_time":1.38272759,"remaining_time":0.1121130479},
{"learn":[0.002543191239],"iteration":925,"passed_time":1.384009159,"remaining_time":0.1106011639},
{"learn":[0.002543180975],"iteration":926,"passed_time":1.385187174,"remaining_time":0.1090816221},
{"learn":[0.002543199283],"iteration":927,"passed_time":1.386361381,"remaining_time":0.107562521},
{"learn":[0.002543178468],"iteration":928,"passed_time":1.38760418,"remaining_time":0.1060494045},
{"learn":[0.002543090716],"iteration":929,"passed_time":1.388887138,"remaining_time":0.1045398921},
{"learn":[0.002543084805],"iteration":930,"passed_time":1.390127002,"remaining_time":0.1030276725},
{"learn":[0.002543084805],"iteration":931,"passed_time":1.391250862,"remaining_time":0.1015075736},
{"learn":[0.002543049022],"iteration":932,"passed_time":1.392445308,"remaining_time":0.09999339295},
{"learn":[0.002543024611],"iteration":933,"passed_time":1.393622283,"remaining_time":0.09847866242},
{"learn":[0.002542895742],"iteration":934,"passed_time":1.394810845,"remaining_time":0.09696545982},
{"learn":[0.002542844364],"iteration":935,"passed_time":1.395971768,"remaining_time":0.09545106105},
{"learn":[0.002542852782],"iteration":936,"passed_time":1.397199496,"remaining_time":0.09394190846},
{"learn":[0.002542823294],"iteration":937,"passed_time":1.398526933,"remaining_time":0.09243994652},
{"learn":[0.002542830506],"iteration":938,"passed_time":1.399819913,"remaining_time":0.09093611787},
{"learn":[0.002542185116],"iteration":939,"passed_time":1.401190809,"remaining_time":0.08943771118},
{"learn":[0.002542185394],"iteration":940,"passed_time":1.402530162,"remaining_time":0.08793759786},
{"learn":[0.002542198997],"iteration":941,"passed_time":1.403884006,"remaining_time":0.08643871801},
{"learn":[0.00254213445],"iteration":942,"passed_time":1.405067905,"remaining_time":0.08492987336},
{"learn":[0.002542094783],"iteration":943,"passed_time":1.406247563,"remaining_time":0.08342146558},
{"learn":[0.002542098666],"iteration":944,"passed_time":1.407437226,"remaining_time":0.08191433593},
{"learn":[0.002541999264],"iteration":945,"passed_time":1.408644466,"remaining_time":0.08040888072},
{"learn":[0.002541946293],"iteration":946,"passed_time":1.409829915,"remaining_time":0.07890283577},
{"learn":[0.0025419564],"iteration":947,"passed_time":1.41100297,"remaining_time":0.07739678739},
{"learn":[0.0025419564],"iteration":948,"passed_time":1.412194019,"remaining_time":0.07589240778},
{"learn":[0.002541958438],"iteration":949,"passed_time":1.41334857,"remaining_time":0.07438676684},
{"learn":[0.002541853968],"iteration":950,"passed_time":1.41455064,"remaining_time":0.07288431267},
{"learn":[0.002541840653],"iteration":951,"passed_time":1.415726931,"remaining_time":0.07138118982},
{"learn":[0.002541816424],"iteration":952,"passed_time":1.416925334,"remaining_time":0.06987984335},
{"learn":[0.002541808657],"iteration":953,"passed_time":1.41809329,"remaining_time":0.06837766389},
{"learn":[0.002541556577],"iteration":954,"passed_time":1.419417559,"remaining_time":0.06688354989},
{"learn":[0.002541559905],"iteration":955,"passed_time":1.420654474,"remaining_time":0.06538577076},
{"learn":[0.002541536206],"iteration":956,"passed_time":1.421885177,"remaining_time":0.06388825769},
{"learn":[0.002538005482],"iteration":957,"passed_time":1.423197052,"remaining_time":0.06239486033},
{"learn":[0.002538011307],"iteration":958,"passed_time":1.424382932,"remaining_time":0.06089645485},
{"learn":[0.002537875844],"iteration":959,"passed_time":1.425597986,"remaining_time":0.05939991608},
{"learn":[0.002537760822],"iteration":960,"passed_time":1.426835191,"remaining_time":0.05790486209},
{"learn":[0.00253772172],"iteration":961,"passed_time":1.428055168,"remaining_time":0.05640966358},
{"learn":[0.00253772921],"iteration":962,"passed_time":1.429246254,"remaining_time":0.05491392668},
{"learn":[0.002537720888],"iteration":963,"passed_time":1.43048388,"remaining_time":0.05342055984},
{"learn":[0.002537594323],"iteration":964,"passed_time":1.431686882,"remaining_time":0.05192646722},
{"learn":[0.002537584892],"iteration":965,"passed_time":1.432878234,"remaining_time":0.05043256725},
{"learn":[0.002537451961],"iteration":966,"passed_time":1.434188323,"remaining_time":0.04894334506},
{"learn":[0.00253745418],"iteration":967,"passed_time":1.435349597,"remaining_time":0.04744957345},
{"learn":[0.002537384796],"iteration":968,"passed_time":1.436612443,"remaining_time":0.04595973761},
{"learn":[0.00253359763],"iteration":969,"passed_time":1.437950204,"remaining_time":0.04447268673},
{"learn":[0.002533102479],"iteration":970,"passed_time":1.439197078,"remaining_time":0.04298322889},
{"learn":[0.002533089623],"iteration":971,"passed_time":1.440422431,"remaining_time":0.04149365028},
{"learn":[0.002533066514],"iteration":972,"passed_time":1.441617047,"remaining_time":0.04000376184},
{"learn":[0.00252953129],"iteration":973,"passed_time":1.442951865,"remaining_time":0.03851822227},
{"learn":[0.002526774439],"iteration":974,"passed_time":1.444288066,"remaining_time":0.03703302733},
{"learn":[0.002526773885],"iteration":975,"passed_time":1.445436228,"remaining_time":0.0355435138},
{"learn":[0.002526606771],"iteration":976,"passed_time":1.446684431,"remaining_time":0.03405705416},
{"learn":[0.002526595953],"iteration":977,"passed_time":1.44791287,"remaining_time":0.03257063716},
{"learn":[0.002526547928],"iteration":978,"passed_time":1.449288873,"remaining_time":0.0310879125},
{"learn":[0.002526499132],"iteration":979,"passed_time":1.450532396,"remaining_time":0.02960270195},
{"learn":[0.002526482645],"iteration":980,"passed_time":1.451785117,"remaining_time":0.02811816231},
{"learn":[0.00252645306],"iteration":981,"passed_time":1.452959986,"remaining_time":0.02663266777},
{"learn":[0.002526448622],"iteration":982,"passed_time":1.454140666,"remaining_time":0.02514790572},
{"learn":[0.002526425779],"iteration":983,"passed_time":1.455353366,"remaining_time":0.02366428237},
{"learn":[0.002522580649],"iteration":984,"passed_time":1.456676141,"remaining_time":0.0221828854},
{"learn":[0.002522555406],"iteration":985,"passed_time":1.457878822,"remaining_time":0.02070010498},
{"learn":[0.002522516475],"iteration":986,"passed_time":1.459079582,"remaining_time":0.01921786684},
{"learn":[0.002522516475],"iteration":987,"passed_time":1.460219944,"remaining_time":0.01773546491},
{"learn":[0.002513480307],"iteration":988,"passed_time":1.461540636,"remaining_time":0.01625576036},
{"learn":[0.002513439893],"iteration":989,"passed_time":1.462733608,"remaining_time":0.01477508695},
{"learn":[0.00251343268],"iteration":990,"passed_time":1.463890574,"remaining_time":0.01329466717},
{"learn":[0.002513305006],"iteration":991,"passed_time":1.465297587,"remaining_time":0.01181691603},
{"learn":[0.00251322894],"iteration":992,"passed_time":1.466593876,"remaining_time":0.01033852682},
{"learn":[0.002510959116],"iteration":993,"passed_time":1.467911499,"remaining_time":0.008860632793},
{"learn":[0.002510937853],"iteration":994,"passed_time":1.469134699,"remaining_time":0.007382586426},
{"learn":[0.002510921946],"iteration":995,"passed_time":1.4703252,"remaining_time":0.00590492048},
{"learn":[0.002510716915],"iteration":996,"passed_time":1.471484316,"remaining_time":0.004427736157},
{"learn":[0.002508145943],"iteration":997,"passed_time":1.472717023,"remaining_time":0.00295133672},
{"learn":[0.002508141505],"iteration":998,"passed_time":1.473894056,"remaining_time":0.001475369426},
{"learn":[0.002508109509],"iteration":999,"passed_time":1.475043467,"remaining_time":0}
]}